{"findCompletedItemsResponse": [{"ack": ["Success"], "version": ["1.13.0"], "timestamp": ["2019-07-02T19:00:02.078Z"], "searchResult": [{"@count": "59", "item": [{"itemId": ["323399790924"], "title": ["Apple MacBook Pro 13\" 512GB 2.3GHz i5 Touch Bar 2018 | Space Gray or Silver"], "globalId": ["EBAY-US"], "primaryCategory": [{"categoryId": ["111422"], "categoryName": ["Apple Laptops"]}], "galleryURL": ["http://thumbs1.ebaystatic.com/pict/323399790924404000000002_2.jpg"], "viewItemURL": ["http://www.ebay.com/itm/Apple-MacBook-Pro-13-512GB-2-3GHz-i5-Touch-Bar-2018-Space-Gray-Silver-/323399790924?var=512462044545"], "paymentMethod": ["PayPal"], "autoPay": ["true"], "postalCode": ["10018"], "location": ["New York,NY,USA"], "country": ["US"], "shippingInfo": [{"shippingServiceCost": [{"@currencyId": "USD", "__value__": "0.0"}], "shippingType": ["Free"], "shipToLocations": ["Worldwide"], "expeditedShipping": ["true"], "oneDayShippingAvailable": ["false"], "handlingTime": ["1"]}], "sellingStatus": [{"currentPrice": [{"@currencyId": "USD", "__value__": "1829.0"}], "convertedCurrentPrice": [{"@currencyId": "USD", "__value__": "1829.0"}], "sellingState": ["EndedWithSales"]}], "listingInfo": [{"bestOfferEnabled": ["false"], "buyItNowAvailable": ["false"], "startTime": ["2018-08-16T20:58:52.000Z"], "endTime": ["2019-05-02T22:40:52.000Z"], "listingType": ["StoreInventory"], "gift": ["false"], "watchCount": ["67"]}], "returnsAccepted": ["true"], "condition": [{"conditionId": ["1000"], "conditionDisplayName": ["New"]}], "isMultiVariationListing": ["true"], "topRatedListing": ["true"]}, {"itemId": ["264280413209"], "title": ["Apple MacBook Pro 13-inch Mid 2018- i7 Quad-Core 2.7Ghz - 512GB SSD - 16GB -Gray"], "globalId": ["EBAY-US"], "primaryCategory": [{"categoryId": ["111422"], "categoryName": ["Apple Laptops"]}], "galleryURL": ["http://thumbs2.ebaystatic.com/m/mclmLSF17EfovVSGm9-O4ww/140.jpg"], "viewItemURL": ["http://www.ebay.com/itm/Apple-MacBook-Pro-13-inch-Mid-2018-i7-Quad-Core-2-7Ghz-512GB-SSD-16GB-Gray-/264280413209"], "paymentMethod": ["PayPal"], "autoPay": ["true"], "postalCode": ["33179"], "location": ["Miami,FL,USA"], "country": ["US"], "shippingInfo": [{"shippingServiceCost": [{"@currencyId": "USD", "__value__": "0.0"}], "shippingType": ["FlatDomesticCalculatedInternational"], "shipToLocations": ["Worldwide"], "expeditedShipping": ["false"], "oneDayShippingAvailable": ["false"], "handlingTime": ["1"]}], "sellingStatus": [{"currentPrice": [{"@currencyId": "USD", "__value__": "2290.0"}], "convertedCurrentPrice": [{"@currencyId": "USD", "__value__": "2290.0"}], "sellingState": ["EndedWithSales"]}], "listingInfo": [{"bestOfferEnabled": ["true"], "buyItNowAvailable": ["false"], "startTime": ["2019-04-12T14:30:59.000Z"], "endTime": ["2019-05-02T19:34:00.000Z"], "listingType": ["StoreInventory"], "gift": ["false"], "watchCount": ["6"]}], "returnsAccepted": ["false"], "condition": [{"conditionId": ["1000"], "conditionDisplayName": ["New"]}], "isMultiVariationListing": ["false"], "topRatedListing": ["false"]}, {"itemId": ["233205076786"], "title": ["Apple Macbook Pro 13\" 8gb 2.3ghz 256gb SSD Space Gray MR9Q2LL/A - Brand New"], "globalId": ["EBAY-US"], "primaryCategory": [{"categoryId": ["111422"], "categoryName": ["Apple Laptops"]}], "galleryURL": ["http://thumbs3.ebaystatic.com/m/mlBUDjFHnD0r8puvjDge9oQ/140.jpg"], "viewItemURL": ["http://www.ebay.com/itm/Apple-Macbook-Pro-13-8gb-2-3ghz-256gb-SSD-Space-Gray-MR9Q2LL-A-Brand-New-/233205076786"], "productId": [{"@type": "ReferenceID", "__value__": "6027566072"}], "paymentMethod": ["PayPal"], "autoPay": ["false"], "postalCode": ["45040"], "location": ["Mason,OH,USA"], "country": ["US"], "shippingInfo": [{"shippingType": ["Calculated"], "shipToLocations": ["Worldwide"], "expeditedShipping": ["false"], "oneDayShippingAvailable": ["false"], "handlingTime": ["3"]}], "sellingStatus": [{"currentPrice": [{"@currencyId": "USD", "__value__": "1599.99"}], "convertedCurrentPrice": [{"@currencyId": "USD", "__value__": "1599.99"}], "sellingState": ["EndedWithSales"]}], "listingInfo": [{"bestOfferEnabled": ["false"], "buyItNowAvailable": ["false"], "startTime": ["2019-04-21T17:33:55.000Z"], "endTime": ["2019-05-02T19:07:22.000Z"], "listingType": ["FixedPrice"], "gift": ["false"], "watchCount": ["1"]}], "returnsAccepted": ["false"], "condition": [{"conditionId": ["1000"], "conditionDisplayName": ["New"]}], "isMultiVariationListing": ["false"], "topRatedListing": ["false"]}, {"itemId": ["283466742565"], "title": ["Sealed Apple MacBook Pro 13-inch 2018 i5 Quad-Core  2.3GHz 256GB SSD 16GB Silver"], "globalId": ["EBAY-US"], "primaryCategory": [{"categoryId": ["111422"], "categoryName": ["Apple Laptops"]}], "galleryURL": ["http://thumbs2.ebaystatic.com/m/m67qaooyr_SNqAlzQp1FA7w/140.jpg"], "viewItemURL": ["http://www.ebay.com/itm/Sealed-Apple-MacBook-Pro-13-inch-2018-i5-Quad-Core-2-3GHz-256GB-SSD-16GB-Silver-/283466742565"], "paymentMethod": ["PayPal"], "autoPay": ["false"], "postalCode": ["98665"], "location": ["Vancouver,WA,USA"], "country": ["US"], "shippingInfo": [{"shippingServiceCost": [{"@currencyId": "USD", "__value__": "30.0"}], "shippingType": ["Flat"], "shipToLocations": ["Worldwide"], "expeditedShipping": ["true"], "oneDayShippingAvailable": ["false"], "handlingTime": ["2"]}], "sellingStatus": [{"currentPrice": [{"@currencyId": "USD", "__value__": "1699.0"}], "convertedCurrentPrice": [{"@currencyId": "USD", "__value__": "1699.0"}], "sellingState": ["EndedWithSales"]}], "listingInfo": [{"bestOfferEnabled": ["true"], "buyItNowAvailable": ["false"], "startTime": ["2019-04-29T06:13:50.000Z"], "endTime": ["2019-05-02T17:15:20.000Z"], "listingType": ["FixedPrice"], "gift": ["false"], "watchCount": ["9"]}], "returnsAccepted": ["false"], "condition": [{"conditionId": ["1000"], "conditionDisplayName": ["New"]}], "isMultiVariationListing": ["false"], "topRatedListing": ["false"]}, {"itemId": ["273824198538"], "title": ["TOP-END 2018 13\" Apple MacBook Pro Retina 2.7 GHz QUAD Core i7 2TB SSD 16GB RAM!"], "globalId": ["EBAY-US"], "primaryCategory": [{"categoryId": ["111422"], "categoryName": ["Apple Laptops"]}], "galleryURL": ["http://thumbs3.ebaystatic.com/m/mg9jkJH2Y-LHbscPSEXo5uQ/140.jpg"], "viewItemURL": ["http://www.ebay.com/itm/TOP-END-2018-13-Apple-MacBook-Pro-Retina-2-7-GHz-QUAD-Core-i7-2TB-SSD-16GB-RAM-/273824198538"], "paymentMethod": ["PayPal"], "autoPay": ["true"], "postalCode": ["93635"], "location": ["Los Banos,CA,USA"], "country": ["US"], "shippingInfo": [{"shippingServiceCost": [{"@currencyId": "USD", "__value__": "0.0"}], "shippingType": ["Free"], "shipToLocations": ["Worldwide"], "expeditedShipping": ["true"], "oneDayShippingAvailable": ["false"], "handlingTime": ["3"]}], "sellingStatus": [{"currentPrice": [{"@currencyId": "USD", "__value__": "3000.0"}], "convertedCurrentPrice": [{"@currencyId": "USD", "__value__": "3000.0"}], "sellingState": ["EndedWithSales"]}], "listingInfo": [{"bestOfferEnabled": ["true"], "buyItNowAvailable": ["false"], "startTime": ["2019-04-27T21:19:51.000Z"], "endTime": ["2019-04-30T20:47:03.000Z"], "listingType": ["FixedPrice"], "gift": ["false"], "watchCount": ["7"]}], "returnsAccepted": ["false"], "condition": [{"conditionId": ["1000"], "conditionDisplayName": ["New"]}], "isMultiVariationListing": ["false"], "topRatedListing": ["false"]}, {"itemId": ["163666653834"], "title": ["MacBook Pro 13\" 2.3GHz i5 8GB 256GB Touch Bar Silver 2018 MR9U2LL/A NEW + EXTRAS"], "globalId": ["EBAY-US"], "primaryCategory": [{"categoryId": ["111422"], "categoryName": ["Apple Laptops"]}], "galleryURL": ["http://thumbs3.ebaystatic.com/m/mx6ZaDsADtOsoTRIKCNQppQ/140.jpg"], "viewItemURL": ["http://www.ebay.com/itm/MacBook-Pro-13-2-3GHz-i5-8GB-256GB-Touch-Bar-Silver-2018-MR9U2LL-A-NEW-EXTRAS-/163666653834"], "productId": [{"@type": "ReferenceID", "__value__": "12027548069"}], "paymentMethod": ["PayPal"], "autoPay": ["true"], "postalCode": ["80916"], "location": ["Colorado Springs,CO,USA"], "country": ["US"], "shippingInfo": [{"shippingServiceCost": [{"@currencyId": "USD", "__value__": "0.0"}], "shippingType": ["Free"], "shipToLocations": ["Worldwide"], "expeditedShipping": ["false"], "oneDayShippingAvailable": ["false"], "handlingTime": ["2"]}], "sellingStatus": [{"currentPrice": [{"@currencyId": "USD", "__value__": "1799.0"}], "convertedCurrentPrice": [{"@currencyId": "USD", "__value__": "1799.0"}], "sellingState": ["EndedWithSales"]}], "listingInfo": [{"bestOfferEnabled": ["false"], "buyItNowAvailable": ["false"], "startTime": ["2019-04-26T17:02:34.000Z"], "endTime": ["2019-04-30T16:54:09.000Z"], "listingType": ["FixedPrice"], "gift": ["false"], "watchCount": ["1"]}], "returnsAccepted": ["false"], "condition": [{"conditionId": ["1000"], "conditionDisplayName": ["New"]}], "isMultiVariationListing": ["false"], "topRatedListing": ["false"]}, {"itemId": ["323791066163"], "title": ["*NEW* Apple MacBook Pro 13\" w/ Touch Bar - Core i5, 8 GB RAM, 256 GB SSD (Gray)"], "globalId": ["EBAY-US"], "primaryCategory": [{"categoryId": ["111422"], "categoryName": ["Apple Laptops"]}], "galleryURL": ["http://thumbs4.ebaystatic.com/m/mftA1jj_mUqI5mOhMww2xjQ/140.jpg"], "viewItemURL": ["http://www.ebay.com/itm/NEW-Apple-MacBook-Pro-13-w-Touch-Bar-Core-i5-8-GB-RAM-256-GB-SSD-Gray-/323791066163"], "productId": [{"@type": "ReferenceID", "__value__": "5021491514"}], "paymentMethod": ["PayPal"], "autoPay": ["true"], "postalCode": ["15086"], "location": ["Warrendale,PA,USA"], "country": ["US"], "shippingInfo": [{"shippingServiceCost": [{"@currencyId": "USD", "__value__": "0.0"}], "shippingType": ["Free"], "shipToLocations": ["Worldwide"], "expeditedShipping": ["true"], "oneDayShippingAvailable": ["true"], "handlingTime": ["1"]}], "sellingStatus": [{"currentPrice": [{"@currencyId": "USD", "__value__": "1624.99"}], "convertedCurrentPrice": [{"@currencyId": "USD", "__value__": "1624.99"}], "sellingState": ["EndedWithSales"]}], "listingInfo": [{"bestOfferEnabled": ["false"], "buyItNowAvailable": ["false"], "startTime": ["2019-04-28T02:16:47.000Z"], "endTime": ["2019-04-30T16:38:18.000Z"], "listingType": ["StoreInventory"], "gift": ["false"], "watchCount": ["1"]}], "returnsAccepted": ["true"], "condition": [{"conditionId": ["1000"], "conditionDisplayName": ["New"]}], "isMultiVariationListing": ["false"], "topRatedListing": ["false"]}, {"itemId": ["283466744323"], "title": ["Sealed Apple MacBook Pro 13-inch 2018 i5 Quad-Core  2.3GHz 256GB 16GB Space grey"], "globalId": ["EBAY-US"], "primaryCategory": [{"categoryId": ["111422"], "categoryName": ["Apple Laptops"]}], "galleryURL": ["http://thumbs4.ebaystatic.com/m/m67qaooyr_SNqAlzQp1FA7w/140.jpg"], "viewItemURL": ["http://www.ebay.com/itm/Sealed-Apple-MacBook-Pro-13-inch-2018-i5-Quad-Core-2-3GHz-256GB-16GB-Space-grey-/283466744323"], "paymentMethod": ["PayPal"], "autoPay": ["false"], "postalCode": ["98665"], "location": ["Vancouver,WA,USA"], "country": ["US"], "shippingInfo": [{"shippingServiceCost": [{"@currencyId": "USD", "__value__": "30.0"}], "shippingType": ["Flat"], "shipToLocations": ["Worldwide"], "expeditedShipping": ["true"], "oneDayShippingAvailable": ["false"], "handlingTime": ["2"]}], "sellingStatus": [{"currentPrice": [{"@currencyId": "USD", "__value__": "1650.0"}], "convertedCurrentPrice": [{"@currencyId": "USD", "__value__": "1650.0"}], "sellingState": ["EndedWithSales"]}], "listingInfo": [{"bestOfferEnabled": ["true"], "buyItNowAvailable": ["false"], "startTime": ["2019-04-29T06:18:24.000Z"], "endTime": ["2019-04-30T05:46:21.000Z"], "listingType": ["FixedPrice"], "gift": ["false"], "watchCount": ["2"]}], "returnsAccepted": ["false"], "condition": [{"conditionId": ["1000"], "conditionDisplayName": ["New"]}], "isMultiVariationListing": ["false"], "topRatedListing": ["false"]}, {"itemId": ["123750590977"], "title": ["NEW Apple MacBook Pro 13\" SPACE GRAY A1989 2.3GHz i5 8GB 512GB MR9R2LL/A 2018"], "globalId": ["EBAY-US"], "primaryCategory": [{"categoryId": ["111422"], "categoryName": ["Apple Laptops"]}], "galleryURL": ["http://thumbs2.ebaystatic.com/m/m7uPZQM9qFfJN_6mPFdDrYQ/140.jpg"], "viewItemURL": ["http://www.ebay.com/itm/NEW-Apple-MacBook-Pro-13-SPACE-GRAY-A1989-2-3GHz-i5-8GB-512GB-MR9R2LL-A-2018-/123750590977"], "paymentMethod": ["PayPal"], "autoPay": ["true"], "postalCode": ["91913"], "location": ["Chula Vista,CA,USA"], "country": ["US"], "shippingInfo": [{"shippingServiceCost": [{"@currencyId": "USD", "__value__": "0.0"}], "shippingType": ["Free"], "shipToLocations": ["Worldwide"], "expeditedShipping": ["true"], "oneDayShippingAvailable": ["false"], "handlingTime": ["1"]}], "sellingStatus": [{"currentPrice": [{"@currencyId": "USD", "__value__": "1640.0"}], "convertedCurrentPrice": [{"@currencyId": "USD", "__value__": "1640.0"}], "sellingState": ["EndedWithSales"]}], "listingInfo": [{"bestOfferEnabled": ["false"], "buyItNowAvailable": ["false"], "startTime": ["2019-04-29T16:37:24.000Z"], "endTime": ["2019-04-30T04:02:41.000Z"], "listingType": ["StoreInventory"], "gift": ["false"]}], "returnsAccepted": ["true"], "condition": [{"conditionId": ["1000"], "conditionDisplayName": ["New"]}], "isMultiVariationListing": ["false"], "topRatedListing": ["true"]}, {"itemId": ["264299085065"], "title": ["Apple MacBook Pro 13-inch Mid 2018 i5 Quad-Core  2.3GHz 256GB SSD 16GB S.GRAY "], "globalId": ["EBAY-US"], "primaryCategory": [{"categoryId": ["111422"], "categoryName": ["Apple Laptops"]}], "galleryURL": ["http://thumbs2.ebaystatic.com/m/mclmLSF17EfovVSGm9-O4ww/140.jpg"], "viewItemURL": ["http://www.ebay.com/itm/Apple-MacBook-Pro-13-inch-Mid-2018-i5-Quad-Core-2-3GHz-256GB-SSD-16GB-S-GRAY-/264299085065"], "paymentMethod": ["PayPal"], "autoPay": ["true"], "postalCode": ["33179"], "location": ["Miami,FL,USA"], "country": ["US"], "shippingInfo": [{"shippingServiceCost": [{"@currencyId": "USD", "__value__": "0.0"}], "shippingType": ["FlatDomesticCalculatedInternational"], "shipToLocations": ["Worldwide"], "expeditedShipping": ["false"], "oneDayShippingAvailable": ["false"], "handlingTime": ["1"]}], "sellingStatus": [{"currentPrice": [{"@currencyId": "USD", "__value__": "1959.0"}], "convertedCurrentPrice": [{"@currencyId": "USD", "__value__": "1959.0"}], "sellingState": ["EndedWithSales"]}], "listingInfo": [{"bestOfferEnabled": ["true"], "buyItNowAvailable": ["false"], "startTime": ["2019-04-26T12:41:05.000Z"], "endTime": ["2019-04-29T21:34:53.000Z"], "listingType": ["StoreInventory"], "gift": ["false"]}], "returnsAccepted": ["false"], "condition": [{"conditionId": ["1000"], "conditionDisplayName": ["New"]}], "isMultiVariationListing": ["false"], "topRatedListing": ["false"]}, {"itemId": ["362631954688"], "title": [" Details zu  Apple MacBook Pro 13\" (2018), i5 2,3 GHz, 8 GB RAM, 256 GB SSD, sil"], "globalId": ["EBAY-US"], "primaryCategory": [{"categoryId": ["111422"], "categoryName": ["Apple Laptops"]}], "galleryURL": ["http://thumbs1.ebaystatic.com/m/m9w-5tO2HC_TPJwIRtnZ4xw/140.jpg"], "viewItemURL": ["http://www.ebay.com/itm/Details-zu-Apple-MacBook-Pro-13-2018-i5-2-3-GHz-8-GB-RAM-256-GB-SSD-sil-/362631954688"], "paymentMethod": ["PayPal"], "autoPay": ["false"], "postalCode": ["28340"], "location": ["Fairmont,NC,USA"], "country": ["US"], "shippingInfo": [{"shippingServiceCost": [{"@currencyId": "USD", "__value__": "1.0"}], "shippingType": ["Flat"], "shipToLocations": ["Worldwide"], "expeditedShipping": ["false"], "oneDayShippingAvailable": ["false"], "handlingTime": ["3"]}], "sellingStatus": [{"currentPrice": [{"@currencyId": "USD", "__value__": "91.0"}], "convertedCurrentPrice": [{"@currencyId": "USD", "__value__": "91.0"}], "sellingState": ["EndedWithSales"]}], "listingInfo": [{"bestOfferEnabled": ["false"], "buyItNowAvailable": ["false"], "startTime": ["2019-04-25T22:12:08.000Z"], "endTime": ["2019-04-26T23:33:17.000Z"], "listingType": ["FixedPrice"], "gift": ["false"], "watchCount": ["2"]}], "returnsAccepted": ["true"], "condition": [{"conditionId": ["1000"], "conditionDisplayName": ["New"]}], "isMultiVariationListing": ["false"], "topRatedListing": ["false"]}, {"itemId": ["163643445027"], "title": ["MacBook Pro 13\" 2.3GHz i5 8GB 256GB Touch Bar Silver 2018 MR9U2LL/A NEW + EXTRAS"], "globalId": ["EBAY-US"], "primaryCategory": [{"categoryId": ["111422"], "categoryName": ["Apple Laptops"]}], "galleryURL": ["http://thumbs4.ebaystatic.com/m/mx6ZaDsADtOsoTRIKCNQppQ/140.jpg"], "viewItemURL": ["http://www.ebay.com/itm/MacBook-Pro-13-2-3GHz-i5-8GB-256GB-Touch-Bar-Silver-2018-MR9U2LL-A-NEW-EXTRAS-/163643445027"], "productId": [{"@type": "ReferenceID", "__value__": "12027548069"}], "paymentMethod": ["PayPal"], "autoPay": ["true"], "postalCode": ["80916"], "location": ["Colorado Springs,CO,USA"], "country": ["US"], "shippingInfo": [{"shippingServiceCost": [{"@currencyId": "USD", "__value__": "0.0"}], "shippingType": ["Free"], "shipToLocations": ["Worldwide"], "expeditedShipping": ["false"], "oneDayShippingAvailable": ["false"], "handlingTime": ["2"]}], "sellingStatus": [{"currentPrice": [{"@currencyId": "USD", "__value__": "1799.0"}], "convertedCurrentPrice": [{"@currencyId": "USD", "__value__": "1799.0"}], "sellingState": ["EndedWithSales"]}], "listingInfo": [{"bestOfferEnabled": ["false"], "buyItNowAvailable": ["false"], "startTime": ["2019-04-10T15:02:39.000Z"], "endTime": ["2019-04-25T09:51:24.000Z"], "listingType": ["FixedPrice"], "gift": ["false"], "watchCount": ["1"]}], "returnsAccepted": ["false"], "condition": [{"conditionId": ["1000"], "conditionDisplayName": ["New"]}], "isMultiVariationListing": ["false"], "topRatedListing": ["false"]}, {"itemId": ["382918786698"], "title": ["MacBook Pro 13\" NIB 2.7 ghz Core i7 with a 1TB SSD 16GB (Mid 2018). Brand New! "], "globalId": ["EBAY-US"], "primaryCategory": [{"categoryId": ["111422"], "categoryName": ["Apple Laptops"]}], "galleryURL": ["http://thumbs3.ebaystatic.com/m/m2X0ZECnLkGZRV3mcecNR4A/140.jpg"], "viewItemURL": ["http://www.ebay.com/itm/MacBook-Pro-13-NIB-2-7-ghz-Core-i7-1TB-SSD-16GB-Mid-2018-Brand-New-/382918786698"], "paymentMethod": ["PayPal"], "autoPay": ["false"], "postalCode": ["22401"], "location": ["Fredericksburg,VA,USA"], "country": ["US"], "shippingInfo": [{"shippingServiceCost": [{"@currencyId": "USD", "__value__": "0.0"}], "shippingType": ["Free"], "shipToLocations": ["Worldwide"], "expeditedShipping": ["false"], "oneDayShippingAvailable": ["false"], "handlingTime": ["0"]}], "sellingStatus": [{"currentPrice": [{"@currencyId": "USD", "__value__": "2300.0"}], "convertedCurrentPrice": [{"@currencyId": "USD", "__value__": "2300.0"}], "sellingState": ["EndedWithSales"]}], "listingInfo": [{"bestOfferEnabled": ["true"], "buyItNowAvailable": ["false"], "startTime": ["2019-04-25T02:56:29.000Z"], "endTime": ["2019-04-25T03:13:37.000Z"], "listingType": ["FixedPrice"], "gift": ["false"]}], "returnsAccepted": ["true"], "condition": [{"conditionId": ["1000"], "conditionDisplayName": ["New"]}], "isMultiVariationListing": ["false"], "topRatedListing": ["false"]}, {"itemId": ["382918383237"], "title": ["MacBook Pro 13\" NIB 2.7 ghz Core i7 with a 1TB SSD 16GB (Mid 2018). Brand New! "], "globalId": ["EBAY-US"], "primaryCategory": [{"categoryId": ["111422"], "categoryName": ["Apple Laptops"]}], "galleryURL": ["http://thumbs2.ebaystatic.com/m/m2X0ZECnLkGZRV3mcecNR4A/140.jpg"], "viewItemURL": ["http://www.ebay.com/itm/MacBook-Pro-13-NIB-2-7-ghz-Core-i7-1TB-SSD-16GB-Mid-2018-Brand-New-/382918383237"], "paymentMethod": ["PayPal"], "autoPay": ["false"], "postalCode": ["22401"], "location": ["Fredericksburg,VA,USA"], "country": ["US"], "shippingInfo": [{"shippingServiceCost": [{"@currencyId": "USD", "__value__": "0.0"}], "shippingType": ["Free"], "shipToLocations": ["Worldwide"], "expeditedShipping": ["false"], "oneDayShippingAvailable": ["false"], "handlingTime": ["0"]}], "sellingStatus": [{"currentPrice": [{"@currencyId": "USD", "__value__": "2399.0"}], "convertedCurrentPrice": [{"@currencyId": "USD", "__value__": "2399.0"}], "sellingState": ["EndedWithSales"]}], "listingInfo": [{"bestOfferEnabled": ["true"], "buyItNowAvailable": ["false"], "startTime": ["2019-04-24T21:22:57.000Z"], "endTime": ["2019-04-25T01:56:23.000Z"], "listingType": ["FixedPrice"], "gift": ["false"], "watchCount": ["1"]}], "returnsAccepted": ["true"], "condition": [{"conditionId": ["1000"], "conditionDisplayName": ["New"]}], "isMultiVariationListing": ["false"], "topRatedListing": ["false"]}, {"itemId": ["113710557828"], "title": ["NEW Apple MacBook Pro 13\" Mid 2018 i7 Quad-Core 2.7Ghz 512 8GB AppleCare+2022"], "globalId": ["EBAY-US"], "primaryCategory": [{"categoryId": ["111422"], "categoryName": ["Apple Laptops"]}], "galleryURL": ["http://thumbs1.ebaystatic.com/m/mg6rp_MO7PrNKXxV_paTnhw/140.jpg"], "viewItemURL": ["http://www.ebay.com/itm/NEW-Apple-MacBook-Pro-13-Mid-2018-i7-Quad-Core-2-7Ghz-512-8GB-AppleCare-2022-/113710557828"], "paymentMethod": ["PayPal"], "autoPay": ["false"], "postalCode": ["94109"], "location": ["San Francisco,CA,USA"], "country": ["US"], "shippingInfo": [{"shippingType": ["Calculated"], "shipToLocations": ["Worldwide"], "expeditedShipping": ["true"], "oneDayShippingAvailable": ["false"], "handlingTime": ["3"]}], "sellingStatus": [{"currentPrice": [{"@currencyId": "USD", "__value__": "1975.0"}], "convertedCurrentPrice": [{"@currencyId": "USD", "__value__": "1975.0"}], "sellingState": ["EndedWithSales"]}], "listingInfo": [{"bestOfferEnabled": ["false"], "buyItNowAvailable": ["false"], "startTime": ["2019-04-07T03:12:48.000Z"], "endTime": ["2019-04-24T18:15:07.000Z"], "listingType": ["FixedPrice"], "gift": ["false"], "watchCount": ["5"]}], "returnsAccepted": ["false"], "condition": [{"conditionId": ["1000"], "conditionDisplayName": ["New"]}], "isMultiVariationListing": ["false"], "topRatedListing": ["false"]}, {"itemId": ["223492211952"], "title": ["Apple MacBook Pro 13\" 512GB 2.3GHz i5 Touch Bar 2018 | Space Gray\u00a0"], "globalId": ["EBAY-US"], "primaryCategory": [{"categoryId": ["111422"], "categoryName": ["Apple Laptops"]}], "galleryURL": ["http://thumbs1.ebaystatic.com/m/mIJtzmrkEksuuhnrJMxEPkg/140.jpg"], "viewItemURL": ["http://www.ebay.com/itm/Apple-MacBook-Pro-13-512GB-2-3GHz-i5-Touch-Bar-2018-Space-Gray-/223492211952"], "paymentMethod": ["PayPal"], "autoPay": ["false"], "postalCode": ["01851"], "location": ["Lowell,MA,USA"], "country": ["US"], "shippingInfo": [{"shippingServiceCost": [{"@currencyId": "USD", "__value__": "10.0"}], "shippingType": ["Flat"], "shipToLocations": ["Worldwide"], "expeditedShipping": ["false"], "oneDayShippingAvailable": ["false"], "handlingTime": ["2"]}], "sellingStatus": [{"currentPrice": [{"@currencyId": "USD", "__value__": "1525.0"}], "convertedCurrentPrice": [{"@currencyId": "USD", "__value__": "1525.0"}], "sellingState": ["EndedWithSales"]}], "listingInfo": [{"bestOfferEnabled": ["true"], "buyItNowAvailable": ["false"], "startTime": ["2019-04-23T17:28:26.000Z"], "endTime": ["2019-04-23T21:49:42.000Z"], "listingType": ["FixedPrice"], "gift": ["false"], "watchCount": ["1"]}], "returnsAccepted": ["false"], "condition": [{"conditionId": ["1000"], "conditionDisplayName": ["New"]}], "isMultiVariationListing": ["false"], "topRatedListing": ["false"]}, {"itemId": ["264291723669"], "title": ["New in Box Apple MacBook Pro 13\" Retina TouchBar, 2.3GHz Quad-Core i5 8GB 512SSD"], "globalId": ["EBAY-US"], "primaryCategory": [{"categoryId": ["111422"], "categoryName": ["Apple Laptops"]}], "galleryURL": ["http://thumbs2.ebaystatic.com/m/mSdOqoSxXGblNFJYOpiSpaA/140.jpg"], "viewItemURL": ["http://www.ebay.com/itm/New-Box-Apple-MacBook-Pro-13-Retina-TouchBar-2-3GHz-Quad-Core-i5-8GB-512SSD-/264291723669"], "productId": [{"@type": "ReferenceID", "__value__": "10022297999"}], "paymentMethod": ["PayPal"], "autoPay": ["true"], "postalCode": ["95817"], "location": ["Sacramento,CA,USA"], "country": ["US"], "shippingInfo": [{"shippingServiceCost": [{"@currencyId": "USD", "__value__": "0.0"}], "shippingType": ["Free"], "shipToLocations": ["Worldwide"], "expeditedShipping": ["false"], "oneDayShippingAvailable": ["false"], "handlingTime": ["1"]}], "sellingStatus": [{"currentPrice": [{"@currencyId": "USD", "__value__": "1834.99"}], "convertedCurrentPrice": [{"@currencyId": "USD", "__value__": "1834.99"}], "sellingState": ["EndedWithSales"]}], "listingInfo": [{"bestOfferEnabled": ["false"], "buyItNowAvailable": ["false"], "startTime": ["2019-04-20T18:16:17.000Z"], "endTime": ["2019-04-23T17:39:04.000Z"], "listingType": ["FixedPrice"], "gift": ["false"], "watchCount": ["3"]}], "returnsAccepted": ["true"], "condition": [{"conditionId": ["1000"], "conditionDisplayName": ["New"]}], "isMultiVariationListing": ["false"], "topRatedListing": ["false"]}, {"itemId": ["254204067714"], "title": ["NEW Apple MacBook Pro 13\" Mid 2018 i5 Quad-Core 2.3Ghz 512GB SSD 16GB  GRAY"], "globalId": ["EBAY-US"], "primaryCategory": [{"categoryId": ["111422"], "categoryName": ["Apple Laptops"]}], "galleryURL": ["http://thumbs3.ebaystatic.com/m/mclmLSF17EfovVSGm9-O4ww/140.jpg"], "viewItemURL": ["http://www.ebay.com/itm/NEW-Apple-MacBook-Pro-13-Mid-2018-i5-Quad-Core-2-3Ghz-512GB-SSD-16GB-GRAY-/254204067714"], "paymentMethod": ["PayPal"], "autoPay": ["true"], "postalCode": ["33179"], "location": ["Miami,FL,USA"], "country": ["US"], "shippingInfo": [{"shippingServiceCost": [{"@currencyId": "USD", "__value__": "0.0"}], "shippingType": ["FlatDomesticCalculatedInternational"], "shipToLocations": ["Worldwide"], "expeditedShipping": ["false"], "oneDayShippingAvailable": ["false"], "handlingTime": ["1"]}], "sellingStatus": [{"currentPrice": [{"@currencyId": "USD", "__value__": "1900.0"}], "convertedCurrentPrice": [{"@currencyId": "USD", "__value__": "1900.0"}], "sellingState": ["EndedWithSales"]}], "listingInfo": [{"bestOfferEnabled": ["true"], "buyItNowAvailable": ["false"], "startTime": ["2019-04-18T17:36:59.000Z"], "endTime": ["2019-04-23T13:18:49.000Z"], "listingType": ["StoreInventory"], "gift": ["false"], "watchCount": ["2"]}], "returnsAccepted": ["false"], "condition": [{"conditionId": ["1000"], "conditionDisplayName": ["New"]}], "isMultiVariationListing": ["false"], "topRatedListing": ["false"]}, {"itemId": ["264288132851"], "title": ["NEW Apple MacBook Pro 13\" w/ Touch Bar i5 8GB 256GB Silver - MR9U2LL/A"], "globalId": ["EBAY-US"], "primaryCategory": [{"categoryId": ["111422"], "categoryName": ["Apple Laptops"]}], "galleryURL": ["http://thumbs4.ebaystatic.com/m/m9txWic52zrpuc1biHC8apw/140.jpg"], "viewItemURL": ["http://www.ebay.com/itm/NEW-Apple-MacBook-Pro-13-w-Touch-Bar-i5-8GB-256GB-Silver-MR9U2LL-A-/264288132851"], "productId": [{"@type": "ReferenceID", "__value__": "12027548069"}], "paymentMethod": ["PayPal"], "autoPay": ["false"], "postalCode": ["92620"], "location": ["Irvine,CA,USA"], "country": ["US"], "shippingInfo": [{"shippingServiceCost": [{"@currencyId": "USD", "__value__": "0.0"}], "shippingType": ["Free"], "shipToLocations": ["Worldwide"], "expeditedShipping": ["false"], "oneDayShippingAvailable": ["false"], "handlingTime": ["2"]}], "sellingStatus": [{"currentPrice": [{"@currencyId": "USD", "__value__": "1599.99"}], "convertedCurrentPrice": [{"@currencyId": "USD", "__value__": "1599.99"}], "sellingState": ["EndedWithSales"]}], "listingInfo": [{"bestOfferEnabled": ["false"], "buyItNowAvailable": ["false"], "startTime": ["2019-04-18T01:38:53.000Z"], "endTime": ["2019-04-22T14:52:15.000Z"], "listingType": ["StoreInventory"], "gift": ["false"], "watchCount": ["1"]}], "returnsAccepted": ["false"], "condition": [{"conditionId": ["1000"], "conditionDisplayName": ["New"]}], "isMultiVariationListing": ["false"], "topRatedListing": ["false"]}, {"itemId": ["233197827604"], "title": ["2018 13\" Apple MacBook Pro 2.3GHz Quad i5 16GB RAM 512GB Touch ID/ Touch Bar"], "globalId": ["EBAY-US"], "subtitle": ["Sealed | Apple Care Plus Till 2022 | MSRP $2469 + Tax"], "primaryCategory": [{"categoryId": ["111422"], "categoryName": ["Apple Laptops"]}], "galleryURL": ["http://thumbs1.ebaystatic.com/m/m3UT0SYYaftoP8Y7N7de_QQ/140.jpg"], "viewItemURL": ["http://www.ebay.com/itm/2018-13-Apple-MacBook-Pro-2-3GHz-Quad-i5-16GB-RAM-512GB-Touch-ID-Touch-Bar-/233197827604"], "paymentMethod": ["PayPal"], "autoPay": ["true"], "postalCode": ["11214"], "location": ["Brooklyn,NY,USA"], "country": ["US"], "shippingInfo": [{"shippingServiceCost": [{"@currencyId": "USD", "__value__": "0.0"}], "shippingType": ["Free"], "shipToLocations": ["Worldwide"], "expeditedShipping": ["true"], "oneDayShippingAvailable": ["false"], "handlingTime": ["1"]}], "sellingStatus": [{"currentPrice": [{"@currencyId": "USD", "__value__": "2099.99"}], "convertedCurrentPrice": [{"@currencyId": "USD", "__value__": "2099.99"}], "sellingState": ["EndedWithSales"]}], "listingInfo": [{"bestOfferEnabled": ["false"], "buyItNowAvailable": ["false"], "startTime": ["2019-04-14T16:50:53.000Z"], "endTime": ["2019-04-21T04:10:20.000Z"], "listingType": ["StoreInventory"], "gift": ["false"], "watchCount": ["18"]}], "returnsAccepted": ["true"], "condition": [{"conditionId": ["1000"], "conditionDisplayName": ["New"]}], "isMultiVariationListing": ["false"], "topRatedListing": ["false"]}, {"itemId": ["233203335436"], "title": ["Apple MacBook Pro 13\" SPACE GRAY 2018 Intel i5 2.3GHz 8GB 256GB SSD w/ Touch Bar"], "globalId": ["EBAY-US"], "primaryCategory": [{"categoryId": ["111422"], "categoryName": ["Apple Laptops"]}], "galleryURL": ["http://thumbs1.ebaystatic.com/m/mMa_kT1bs1ZnG4cdAJjpgFA/140.jpg"], "viewItemURL": ["http://www.ebay.com/itm/Apple-MacBook-Pro-13-SPACE-GRAY-2018-Intel-i5-2-3GHz-8GB-256GB-SSD-w-Touch-Bar-/233203335436"], "productId": [{"@type": "ReferenceID", "__value__": "6027566072"}], "paymentMethod": ["CashOnPickup", "PayPal"], "autoPay": ["false"], "postalCode": ["72211"], "location": ["Little Rock,AR,USA"], "country": ["US"], "shippingInfo": [{"shippingServiceCost": [{"@currencyId": "USD", "__value__": "0.0"}], "shippingType": ["Free"], "shipToLocations": ["Worldwide"], "expeditedShipping": ["false"], "oneDayShippingAvailable": ["false"], "handlingTime": ["1"]}], "sellingStatus": [{"currentPrice": [{"@currencyId": "USD", "__value__": "1650.01"}], "convertedCurrentPrice": [{"@currencyId": "USD", "__value__": "1650.01"}], "sellingState": ["EndedWithSales"]}], "listingInfo": [{"bestOfferEnabled": ["false"], "buyItNowAvailable": ["false"], "startTime": ["2019-04-19T16:19:44.000Z"], "endTime": ["2019-04-20T16:24:03.000Z"], "listingType": ["StoreInventory"], "gift": ["false"], "watchCount": ["6"]}], "returnsAccepted": ["true"], "condition": [{"conditionId": ["1000"], "conditionDisplayName": ["New"]}], "isMultiVariationListing": ["false"], "topRatedListing": ["false"]}, {"itemId": ["153455102687"], "title": ["2018 MacBook Pro 13 Inch 2.3GHz/ 8GB/128GB. Never Used."], "globalId": ["EBAY-US"], "primaryCategory": [{"categoryId": ["111422"], "categoryName": ["Apple Laptops"]}], "galleryURL": ["http://thumbs4.ebaystatic.com/m/mzTCU3ri4x9_jjPguXPp7_g/140.jpg"], "viewItemURL": ["http://www.ebay.com/itm/2018-MacBook-Pro-13-Inch-2-3GHz-8GB-128GB-Never-Used-/153455102687"], "paymentMethod": ["PayPal"], "autoPay": ["false"], "postalCode": ["07836"], "location": ["Flanders,NJ,USA"], "country": ["US"], "shippingInfo": [{"shippingType": ["Calculated"], "shipToLocations": ["Worldwide"], "expeditedShipping": ["true"], "oneDayShippingAvailable": ["false"], "handlingTime": ["3"]}], "sellingStatus": [{"currentPrice": [{"@currencyId": "USD", "__value__": "1200.0"}], "convertedCurrentPrice": [{"@currencyId": "USD", "__value__": "1200.0"}], "sellingState": ["EndedWithSales"]}], "listingInfo": [{"bestOfferEnabled": ["true"], "buyItNowAvailable": ["false"], "startTime": ["2019-04-17T14:11:06.000Z"], "endTime": ["2019-04-20T11:41:13.000Z"], "listingType": ["FixedPrice"], "gift": ["false"], "watchCount": ["7"]}], "returnsAccepted": ["false"], "condition": [{"conditionId": ["1000"], "conditionDisplayName": ["New"]}], "isMultiVariationListing": ["false"], "topRatedListing": ["false"]}, {"itemId": ["362625038507"], "title": ["APPLE MACBOOK PRO 13\" | MR9Q2LL/A | CORE I5-8259U | 256GB | 8GB | FACTORY SEALED"], "globalId": ["EBAY-US"], "primaryCategory": [{"categoryId": ["111422"], "categoryName": ["Apple Laptops"]}], "galleryURL": ["http://thumbs4.ebaystatic.com/m/mpHJAmx206jeU4f5tOXLhAA/140.jpg"], "viewItemURL": ["http://www.ebay.com/itm/APPLE-MACBOOK-PRO-13-MR9Q2LL-A-CORE-I5-8259U-256GB-8GB-FACTORY-SEALED-/362625038507"], "paymentMethod": ["PayPal"], "autoPay": ["false"], "postalCode": ["44224"], "location": ["Stow,OH,USA"], "country": ["US"], "shippingInfo": [{"shippingType": ["Calculated"], "shipToLocations": ["Worldwide"], "expeditedShipping": ["false"], "oneDayShippingAvailable": ["false"], "handlingTime": ["3"]}], "sellingStatus": [{"currentPrice": [{"@currencyId": "USD", "__value__": "1390.0"}], "convertedCurrentPrice": [{"@currencyId": "USD", "__value__": "1390.0"}], "sellingState": ["EndedWithSales"]}], "listingInfo": [{"bestOfferEnabled": ["true"], "buyItNowAvailable": ["false"], "startTime": ["2019-04-19T22:30:08.000Z"], "endTime": ["2019-04-19T22:37:04.000Z"], "listingType": ["FixedPrice"], "gift": ["false"]}], "returnsAccepted": ["true"], "galleryPlusPictureURL": ["http://galleryplus.ebayimg.com/ws/web/362625038507_1_0_1.jpg"], "condition": [{"conditionId": ["1000"], "conditionDisplayName": ["New"]}], "isMultiVariationListing": ["false"], "topRatedListing": ["false"]}, {"itemId": ["133023765695"], "title": ["MacBook Pro13\" Touch Bar 256GB Core i5 8GB Memory 2018 Brand new "], "globalId": ["EBAY-US"], "primaryCategory": [{"categoryId": ["111422"], "categoryName": ["Apple Laptops"]}], "galleryURL": ["http://thumbs4.ebaystatic.com/m/m__Ik_gMKZNKcvZHFyNXVrQ/140.jpg"], "viewItemURL": ["http://www.ebay.com/itm/MacBook-Pro13-Touch-Bar-256GB-Core-i5-8GB-Memory-2018-Brand-new-/133023765695"], "paymentMethod": ["PayPal"], "autoPay": ["false"], "postalCode": ["70118"], "location": ["New Orleans,LA,USA"], "country": ["US"], "shippingInfo": [{"shippingServiceCost": [{"@currencyId": "USD", "__value__": "0.0"}], "shippingType": ["Free"], "shipToLocations": ["Worldwide"], "expeditedShipping": ["true"], "oneDayShippingAvailable": ["false"], "handlingTime": ["2"]}], "sellingStatus": [{"currentPrice": [{"@currencyId": "USD", "__value__": "1350.0"}], "convertedCurrentPrice": [{"@currencyId": "USD", "__value__": "1350.0"}], "sellingState": ["EndedWithSales"]}], "listingInfo": [{"bestOfferEnabled": ["true"], "buyItNowAvailable": ["false"], "startTime": ["2019-04-15T23:21:59.000Z"], "endTime": ["2019-04-19T21:57:16.000Z"], "listingType": ["FixedPrice"], "gift": ["false"], "watchCount": ["1"]}], "returnsAccepted": ["false"], "condition": [{"conditionId": ["1000"], "conditionDisplayName": ["New"]}], "isMultiVariationListing": ["false"], "topRatedListing": ["false"]}, {"itemId": ["254204439318"], "title": ["Apple MacBook Pro 13-inch Mid 2018 i5 Quad-Core  2.3GHz 256GB SSD 16GB S.GRAY "], "globalId": ["EBAY-US"], "primaryCategory": [{"categoryId": ["111422"], "categoryName": ["Apple Laptops"]}], "galleryURL": ["http://thumbs3.ebaystatic.com/m/mclmLSF17EfovVSGm9-O4ww/140.jpg"], "viewItemURL": ["http://www.ebay.com/itm/Apple-MacBook-Pro-13-inch-Mid-2018-i5-Quad-Core-2-3GHz-256GB-SSD-16GB-S-GRAY-/254204439318"], "paymentMethod": ["PayPal"], "autoPay": ["true"], "postalCode": ["33179"], "location": ["Miami,FL,USA"], "country": ["US"], "shippingInfo": [{"shippingServiceCost": [{"@currencyId": "USD", "__value__": "0.0"}], "shippingType": ["FlatDomesticCalculatedInternational"], "shipToLocations": ["Worldwide"], "expeditedShipping": ["false"], "oneDayShippingAvailable": ["false"], "handlingTime": ["1"]}], "sellingStatus": [{"currentPrice": [{"@currencyId": "USD", "__value__": "1799.0"}], "convertedCurrentPrice": [{"@currencyId": "USD", "__value__": "1799.0"}], "sellingState": ["EndedWithSales"]}], "listingInfo": [{"bestOfferEnabled": ["true"], "buyItNowAvailable": ["false"], "startTime": ["2019-04-19T01:57:40.000Z"], "endTime": ["2019-04-19T17:31:15.000Z"], "listingType": ["StoreInventory"], "gift": ["false"]}], "returnsAccepted": ["false"], "condition": [{"conditionId": ["1000"], "conditionDisplayName": ["New"]}], "isMultiVariationListing": ["false"], "topRatedListing": ["false"]}, {"itemId": ["254204026639"], "title": ["Apple MacBook Pro 13-inch Mid 2018 i5 Quad-Core  2.3GHz 256GB SSD 16GB S.GRAY "], "globalId": ["EBAY-US"], "primaryCategory": [{"categoryId": ["111422"], "categoryName": ["Apple Laptops"]}], "galleryURL": ["http://thumbs4.ebaystatic.com/m/mclmLSF17EfovVSGm9-O4ww/140.jpg"], "viewItemURL": ["http://www.ebay.com/itm/Apple-MacBook-Pro-13-inch-Mid-2018-i5-Quad-Core-2-3GHz-256GB-SSD-16GB-S-GRAY-/254204026639"], "paymentMethod": ["PayPal"], "autoPay": ["true"], "postalCode": ["33179"], "location": ["Miami,FL,USA"], "country": ["US"], "shippingInfo": [{"shippingServiceCost": [{"@currencyId": "USD", "__value__": "0.0"}], "shippingType": ["FlatDomesticCalculatedInternational"], "shipToLocations": ["Worldwide"], "expeditedShipping": ["false"], "oneDayShippingAvailable": ["false"], "handlingTime": ["1"]}], "sellingStatus": [{"currentPrice": [{"@currencyId": "USD", "__value__": "1799.0"}], "convertedCurrentPrice": [{"@currencyId": "USD", "__value__": "1799.0"}], "sellingState": ["EndedWithSales"]}], "listingInfo": [{"bestOfferEnabled": ["true"], "buyItNowAvailable": ["false"], "startTime": ["2019-04-18T16:39:56.000Z"], "endTime": ["2019-04-18T21:46:12.000Z"], "listingType": ["StoreInventory"], "gift": ["false"], "watchCount": ["2"]}], "returnsAccepted": ["false"], "condition": [{"conditionId": ["1000"], "conditionDisplayName": ["New"]}], "isMultiVariationListing": ["false"], "topRatedListing": ["false"]}, {"itemId": ["312576647349"], "title": ["NEW 2018 MacBook Pro 13\" Touchbar - Intel i5 2.3GHz / 256GB - MR9Q2LL/A  SEALED!"], "globalId": ["EBAY-US"], "primaryCategory": [{"categoryId": ["111422"], "categoryName": ["Apple Laptops"]}], "galleryURL": ["http://thumbs2.ebaystatic.com/m/myD-ZF6UlL0RXYjDVHYXnLQ/140.jpg"], "viewItemURL": ["http://www.ebay.com/itm/NEW-2018-MacBook-Pro-13-Touchbar-Intel-i5-2-3GHz-256GB-MR9Q2LL-A-SEALED-/312576647349"], "paymentMethod": ["PayPal"], "autoPay": ["true"], "postalCode": ["90012"], "location": ["Los Angeles,CA,USA"], "country": ["US"], "shippingInfo": [{"shippingServiceCost": [{"@currencyId": "USD", "__value__": "0.0"}], "shippingType": ["Free"], "shipToLocations": ["Worldwide"], "expeditedShipping": ["false"], "oneDayShippingAvailable": ["false"], "handlingTime": ["1"]}], "sellingStatus": [{"currentPrice": [{"@currencyId": "USD", "__value__": "1649.95"}], "convertedCurrentPrice": [{"@currencyId": "USD", "__value__": "1649.95"}], "sellingState": ["EndedWithSales"]}], "listingInfo": [{"bestOfferEnabled": ["false"], "buyItNowAvailable": ["false"], "startTime": ["2019-04-17T20:13:13.000Z"], "endTime": ["2019-04-18T20:13:14.000Z"], "listingType": ["StoreInventory"], "gift": ["false"], "watchCount": ["3"]}], "returnsAccepted": ["false"], "condition": [{"conditionId": ["1000"], "conditionDisplayName": ["New"]}], "isMultiVariationListing": ["false"], "topRatedListing": ["false"]}, {"itemId": ["183779374144"], "title": ["2018 MacBook Pro 13 Inch 2.3GHz 16gb 128gb"], "globalId": ["EBAY-US"], "primaryCategory": [{"categoryId": ["111422"], "categoryName": ["Apple Laptops"]}], "galleryURL": ["http://thumbs1.ebaystatic.com/m/m9ozNaO5DC4O-9KkLFyLIQA/140.jpg"], "viewItemURL": ["http://www.ebay.com/itm/2018-MacBook-Pro-13-Inch-2-3GHz-16gb-128gb-/183779374144"], "paymentMethod": ["PayPal"], "autoPay": ["false"], "postalCode": ["55102"], "location": ["Saint Paul,MN,USA"], "country": ["US"], "shippingInfo": [{"shippingType": ["Calculated"], "shipToLocations": ["Worldwide"], "expeditedShipping": ["true"], "oneDayShippingAvailable": ["false"], "handlingTime": ["3"]}], "sellingStatus": [{"currentPrice": [{"@currencyId": "USD", "__value__": "1000.0"}], "convertedCurrentPrice": [{"@currencyId": "USD", "__value__": "1000.0"}], "sellingState": ["EndedWithSales"]}], "listingInfo": [{"bestOfferEnabled": ["true"], "buyItNowAvailable": ["false"], "startTime": ["2019-04-18T12:15:53.000Z"], "endTime": ["2019-04-18T17:55:21.000Z"], "listingType": ["FixedPrice"], "gift": ["false"], "watchCount": ["5"]}], "returnsAccepted": ["false"], "condition": [{"conditionId": ["1000"], "conditionDisplayName": ["New"]}], "isMultiVariationListing": ["false"], "topRatedListing": ["false"]}, {"itemId": ["202656459828"], "title": ["NEW 2018 MACBOOK PRO 13\" QUAD CORE i7 2.7GHZ, 16GB, 1TB SSD, TOUCHBAR"], "globalId": ["EBAY-US"], "primaryCategory": [{"categoryId": ["111422"], "categoryName": ["Apple Laptops"]}], "galleryURL": ["http://thumbs1.ebaystatic.com/m/mRzCCxw_457Rz1wabWQGCTg/140.jpg"], "viewItemURL": ["http://www.ebay.com/itm/NEW-2018-MACBOOK-PRO-13-QUAD-CORE-i7-2-7GHZ-16GB-1TB-SSD-TOUCHBAR-/202656459828"], "paymentMethod": ["PayPal"], "autoPay": ["true"], "postalCode": ["90064"], "location": ["Los Angeles,CA,USA"], "country": ["US"], "shippingInfo": [{"shippingType": ["Calculated"], "shipToLocations": ["Worldwide"], "expeditedShipping": ["false"], "oneDayShippingAvailable": ["false"], "handlingTime": ["1"]}], "sellingStatus": [{"currentPrice": [{"@currencyId": "USD", "__value__": "2599.0"}], "convertedCurrentPrice": [{"@currencyId": "USD", "__value__": "2599.0"}], "sellingState": ["EndedWithSales"]}], "listingInfo": [{"bestOfferEnabled": ["false"], "buyItNowAvailable": ["false"], "startTime": ["2019-04-18T05:27:42.000Z"], "endTime": ["2019-04-18T15:43:59.000Z"], "listingType": ["StoreInventory"], "gift": ["false"], "watchCount": ["1"]}], "returnsAccepted": ["false"], "condition": [{"conditionId": ["1000"], "conditionDisplayName": ["New"]}], "isMultiVariationListing": ["false"], "topRatedListing": ["false"]}, {"itemId": ["183779260771"], "title": ["2018 MacBook Pro 13 Inch 2.3GHz 16gb 128gb"], "globalId": ["EBAY-US"], "primaryCategory": [{"categoryId": ["111422"], "categoryName": ["Apple Laptops"]}], "galleryURL": ["http://thumbs4.ebaystatic.com/m/m9ozNaO5DC4O-9KkLFyLIQA/140.jpg"], "viewItemURL": ["http://www.ebay.com/itm/2018-MacBook-Pro-13-Inch-2-3GHz-16gb-128gb-/183779260771"], "paymentMethod": ["PayPal"], "autoPay": ["false"], "postalCode": ["55102"], "location": ["Saint Paul,MN,USA"], "country": ["US"], "shippingInfo": [{"shippingType": ["Calculated"], "shipToLocations": ["Worldwide"], "expeditedShipping": ["true"], "oneDayShippingAvailable": ["false"], "handlingTime": ["3"]}], "sellingStatus": [{"currentPrice": [{"@currencyId": "USD", "__value__": "1000.0"}], "convertedCurrentPrice": [{"@currencyId": "USD", "__value__": "1000.0"}], "sellingState": ["EndedWithSales"]}], "listingInfo": [{"bestOfferEnabled": ["false"], "buyItNowAvailable": ["false"], "startTime": ["2019-04-18T10:09:25.000Z"], "endTime": ["2019-04-18T11:23:05.000Z"], "listingType": ["FixedPrice"], "gift": ["false"]}], "returnsAccepted": ["false"], "condition": [{"conditionId": ["1000"], "conditionDisplayName": ["New"]}], "isMultiVariationListing": ["false"], "topRatedListing": ["false"]}, {"itemId": ["153451379670"], "title": ["Apple MacBook Pro 13-inch  2018 i5 Quad-Core  2.3GHz 1TB SSD 16GB S.GRAY "], "globalId": ["EBAY-US"], "primaryCategory": [{"categoryId": ["111422"], "categoryName": ["Apple Laptops"]}], "galleryURL": ["http://thumbs3.ebaystatic.com/m/mAIXlJF5PPiy6rVNKe2UTkg/140.jpg"], "viewItemURL": ["http://www.ebay.com/itm/Apple-MacBook-Pro-13-inch-2018-i5-Quad-Core-2-3GHz-1TB-SSD-16GB-S-GRAY-/153451379670"], "paymentMethod": ["PayPal"], "autoPay": ["false"], "postalCode": ["60616"], "location": ["Chicago,IL,USA"], "country": ["US"], "shippingInfo": [{"shippingType": ["Calculated"], "shipToLocations": ["Worldwide"], "expeditedShipping": ["true"], "oneDayShippingAvailable": ["false"], "handlingTime": ["2"]}], "sellingStatus": [{"currentPrice": [{"@currencyId": "USD", "__value__": "2089.99"}], "convertedCurrentPrice": [{"@currencyId": "USD", "__value__": "2089.99"}], "sellingState": ["EndedWithSales"]}], "listingInfo": [{"bestOfferEnabled": ["false"], "buyItNowAvailable": ["false"], "startTime": ["2019-04-14T14:42:34.000Z"], "endTime": ["2019-04-18T08:07:27.000Z"], "listingType": ["FixedPrice"], "gift": ["false"], "watchCount": ["7"]}], "returnsAccepted": ["true"], "condition": [{"conditionId": ["1000"], "conditionDisplayName": ["New"]}], "isMultiVariationListing": ["false"], "topRatedListing": ["false"]}, {"itemId": ["153455095428"], "title": ["2018 MacBook Pro 13 Inch 2.3GHz/ 8GB/128GB"], "globalId": ["EBAY-US"], "primaryCategory": [{"categoryId": ["111422"], "categoryName": ["Apple Laptops"]}], "galleryURL": ["http://thumbs1.ebaystatic.com/m/mjrk2drcM11kvqEnWhdyTLQ/140.jpg"], "viewItemURL": ["http://www.ebay.com/itm/2018-MacBook-Pro-13-Inch-2-3GHz-8GB-128GB-/153455095428"], "paymentMethod": ["PayPal"], "autoPay": ["false"], "postalCode": ["07836"], "location": ["Flanders,NJ,USA"], "country": ["US"], "shippingInfo": [{"shippingType": ["Calculated"], "shipToLocations": ["Worldwide"], "expeditedShipping": ["true"], "oneDayShippingAvailable": ["false"], "handlingTime": ["3"]}], "sellingStatus": [{"currentPrice": [{"@currencyId": "USD", "__value__": "1200.0"}], "convertedCurrentPrice": [{"@currencyId": "USD", "__value__": "1200.0"}], "sellingState": ["EndedWithSales"]}], "listingInfo": [{"bestOfferEnabled": ["true"], "buyItNowAvailable": ["false"], "startTime": ["2019-04-17T14:00:07.000Z"], "endTime": ["2019-04-18T05:12:33.000Z"], "listingType": ["FixedPrice"], "gift": ["false"]}], "returnsAccepted": ["false"], "condition": [{"conditionId": ["1000"], "conditionDisplayName": ["New"]}], "isMultiVariationListing": ["false"], "topRatedListing": ["false"]}, {"itemId": ["223438079242"], "title": ["Apple MacBook Pro 13\" SPACE GRAY 2018 Intel i5 2.3GHz 8GB 256GB SSD w/ Touch Bar"], "globalId": ["EBAY-US"], "primaryCategory": [{"categoryId": ["111422"], "categoryName": ["Apple Laptops"]}], "galleryURL": ["http://thumbs3.ebaystatic.com/m/mMa_kT1bs1ZnG4cdAJjpgFA/140.jpg"], "viewItemURL": ["http://www.ebay.com/itm/Apple-MacBook-Pro-13-SPACE-GRAY-2018-Intel-i5-2-3GHz-8GB-256GB-SSD-w-Touch-Bar-/223438079242"], "productId": [{"@type": "ReferenceID", "__value__": "6027566072"}], "paymentMethod": ["CashOnPickup", "PayPal"], "autoPay": ["false"], "postalCode": ["72211"], "location": ["Little Rock,AR,USA"], "country": ["US"], "shippingInfo": [{"shippingServiceCost": [{"@currencyId": "USD", "__value__": "0.0"}], "shippingType": ["Free"], "shipToLocations": ["Worldwide"], "expeditedShipping": ["false"], "oneDayShippingAvailable": ["false"], "handlingTime": ["1"]}], "sellingStatus": [{"currentPrice": [{"@currencyId": "USD", "__value__": "1650.01"}], "convertedCurrentPrice": [{"@currencyId": "USD", "__value__": "1650.01"}], "sellingState": ["EndedWithSales"]}], "listingInfo": [{"bestOfferEnabled": ["false"], "buyItNowAvailable": ["false"], "startTime": ["2019-03-06T20:53:23.000Z"], "endTime": ["2019-04-18T03:52:08.000Z"], "listingType": ["StoreInventory"], "gift": ["false"], "watchCount": ["43"]}], "returnsAccepted": ["true"], "condition": [{"conditionId": ["1000"], "conditionDisplayName": ["New"]}], "isMultiVariationListing": ["false"], "topRatedListing": ["false"]}, {"itemId": ["183775828236"], "title": ["2018 MacBook Pro 13 Inch 2.3GHz 16gb 128gb"], "globalId": ["EBAY-US"], "primaryCategory": [{"categoryId": ["111422"], "categoryName": ["Apple Laptops"]}], "galleryURL": ["http://thumbs1.ebaystatic.com/m/myxP-iEP2buLFygNwqkVolA/140.jpg"], "viewItemURL": ["http://www.ebay.com/itm/2018-MacBook-Pro-13-Inch-2-3GHz-16gb-128gb-/183775828236"], "paymentMethod": ["PayPal"], "autoPay": ["false"], "postalCode": ["55102"], "location": ["Saint Paul,MN,USA"], "country": ["US"], "shippingInfo": [{"shippingType": ["Calculated"], "shipToLocations": ["Worldwide"], "expeditedShipping": ["true"], "oneDayShippingAvailable": ["false"], "handlingTime": ["3"]}], "sellingStatus": [{"currentPrice": [{"@currencyId": "USD", "__value__": "1299.0"}], "convertedCurrentPrice": [{"@currencyId": "USD", "__value__": "1299.0"}], "sellingState": ["EndedWithSales"]}], "listingInfo": [{"bestOfferEnabled": ["true"], "buyItNowAvailable": ["false"], "startTime": ["2019-04-15T17:49:08.000Z"], "endTime": ["2019-04-18T02:00:37.000Z"], "listingType": ["FixedPrice"], "gift": ["false"], "watchCount": ["6"]}], "returnsAccepted": ["false"], "condition": [{"conditionId": ["1000"], "conditionDisplayName": ["New"]}], "isMultiVariationListing": ["false"], "topRatedListing": ["false"]}, {"itemId": ["254200081827"], "title": ["Apple MacBook Pro 13-inch Mid 2018 i5 Quad-Core  2.3GHz 256GB SSD 16GB S.GRAY "], "globalId": ["EBAY-US"], "primaryCategory": [{"categoryId": ["111422"], "categoryName": ["Apple Laptops"]}], "galleryURL": ["http://thumbs4.ebaystatic.com/m/mclmLSF17EfovVSGm9-O4ww/140.jpg"], "viewItemURL": ["http://www.ebay.com/itm/Apple-MacBook-Pro-13-inch-Mid-2018-i5-Quad-Core-2-3GHz-256GB-SSD-16GB-S-GRAY-/254200081827"], "paymentMethod": ["PayPal"], "autoPay": ["true"], "postalCode": ["33179"], "location": ["Miami,FL,USA"], "country": ["US"], "shippingInfo": [{"shippingServiceCost": [{"@currencyId": "USD", "__value__": "0.0"}], "shippingType": ["FlatDomesticCalculatedInternational"], "shipToLocations": ["Worldwide"], "expeditedShipping": ["false"], "oneDayShippingAvailable": ["false"], "handlingTime": ["1"]}], "sellingStatus": [{"currentPrice": [{"@currencyId": "USD", "__value__": "1800.0"}], "convertedCurrentPrice": [{"@currencyId": "USD", "__value__": "1800.0"}], "sellingState": ["EndedWithSales"]}], "listingInfo": [{"bestOfferEnabled": ["true"], "buyItNowAvailable": ["false"], "startTime": ["2019-04-14T21:57:40.000Z"], "endTime": ["2019-04-17T16:34:16.000Z"], "listingType": ["StoreInventory"], "gift": ["false"], "watchCount": ["7"]}], "returnsAccepted": ["false"], "condition": [{"conditionId": ["1000"], "conditionDisplayName": ["New"]}], "isMultiVariationListing": ["false"], "topRatedListing": ["false"]}, {"itemId": ["264285247184"], "title": ["Apple MacBook Pro 13\" SPACE GRAY 2018 Intel i5 2.3GHz 8GB 256GB SSD w/ Touch Bar"], "globalId": ["EBAY-US"], "primaryCategory": [{"categoryId": ["111422"], "categoryName": ["Apple Laptops"]}], "galleryURL": ["http://thumbs1.ebaystatic.com/m/mehlaLBu97vlyQPCrdJdo8w/140.jpg"], "viewItemURL": ["http://www.ebay.com/itm/Apple-MacBook-Pro-13-SPACE-GRAY-2018-Intel-i5-2-3GHz-8GB-256GB-SSD-w-Touch-Bar-/264285247184"], "productId": [{"@type": "ReferenceID", "__value__": "6027566072"}], "paymentMethod": ["PayPal"], "autoPay": ["false"], "postalCode": ["85747"], "location": ["Tucson,AZ,USA"], "country": ["US"], "shippingInfo": [{"shippingServiceCost": [{"@currencyId": "USD", "__value__": "0.0"}], "shippingType": ["Free"], "shipToLocations": ["Worldwide"], "expeditedShipping": ["true"], "oneDayShippingAvailable": ["false"], "handlingTime": ["1"]}], "sellingStatus": [{"currentPrice": [{"@currencyId": "USD", "__value__": "1550.0"}], "convertedCurrentPrice": [{"@currencyId": "USD", "__value__": "1550.0"}], "sellingState": ["EndedWithSales"]}], "listingInfo": [{"bestOfferEnabled": ["false"], "buyItNowAvailable": ["false"], "startTime": ["2019-04-16T00:33:26.000Z"], "endTime": ["2019-04-16T01:35:53.000Z"], "listingType": ["FixedPrice"], "gift": ["false"], "watchCount": ["1"]}], "returnsAccepted": ["false"], "condition": [{"conditionId": ["1000"], "conditionDisplayName": ["New"]}], "isMultiVariationListing": ["false"], "topRatedListing": ["false"]}, {"itemId": ["183775372964"], "title": ["2018 MacBook Pro 13 Inch 2.3GHz 16gb 128gb"], "globalId": ["EBAY-US"], "primaryCategory": [{"categoryId": ["111422"], "categoryName": ["Apple Laptops"]}], "galleryURL": ["http://thumbs1.ebaystatic.com/m/myxP-iEP2buLFygNwqkVolA/140.jpg"], "viewItemURL": ["http://www.ebay.com/itm/2018-MacBook-Pro-13-Inch-2-3GHz-16gb-128gb-/183775372964"], "paymentMethod": ["PayPal"], "autoPay": ["false"], "postalCode": ["55102"], "location": ["Saint Paul,MN,USA"], "country": ["US"], "shippingInfo": [{"shippingType": ["Calculated"], "shipToLocations": ["Worldwide"], "expeditedShipping": ["true"], "oneDayShippingAvailable": ["false"], "handlingTime": ["3"]}], "sellingStatus": [{"currentPrice": [{"@currencyId": "USD", "__value__": "1200.0"}], "convertedCurrentPrice": [{"@currencyId": "USD", "__value__": "1200.0"}], "sellingState": ["EndedWithSales"]}], "listingInfo": [{"bestOfferEnabled": ["true"], "buyItNowAvailable": ["false"], "startTime": ["2019-04-15T10:21:52.000Z"], "endTime": ["2019-04-15T17:31:38.000Z"], "listingType": ["FixedPrice"], "gift": ["false"]}], "returnsAccepted": ["false"], "condition": [{"conditionId": ["1000"], "conditionDisplayName": ["New"]}], "isMultiVariationListing": ["false"], "topRatedListing": ["false"]}, {"itemId": ["183774683950"], "title": ["Apple MacBook Pro 13\" SPACE GRAY 2018 Intel i5 2.3GHz 8GB 256GB SSD w/ Touch Bar"], "globalId": ["EBAY-US"], "primaryCategory": [{"categoryId": ["111422"], "categoryName": ["Apple Laptops"]}], "galleryURL": ["http://thumbs3.ebaystatic.com/m/mdGyVbN-XrwYOrYGdDwlFwA/140.jpg"], "viewItemURL": ["http://www.ebay.com/itm/Apple-MacBook-Pro-13-SPACE-GRAY-2018-Intel-i5-2-3GHz-8GB-256GB-SSD-w-Touch-Bar-/183774683950"], "productId": [{"@type": "ReferenceID", "__value__": "6027566072"}], "paymentMethod": ["PayPal"], "autoPay": ["false"], "postalCode": ["11226"], "location": ["Brooklyn,NY,USA"], "country": ["US"], "shippingInfo": [{"shippingServiceCost": [{"@currencyId": "USD", "__value__": "0.0"}], "shippingType": ["Free"], "shipToLocations": ["Worldwide"], "expeditedShipping": ["false"], "oneDayShippingAvailable": ["false"], "handlingTime": ["3"]}], "sellingStatus": [{"currentPrice": [{"@currencyId": "USD", "__value__": "1649.0"}], "convertedCurrentPrice": [{"@currencyId": "USD", "__value__": "1649.0"}], "sellingState": ["EndedWithSales"]}], "listingInfo": [{"bestOfferEnabled": ["false"], "buyItNowAvailable": ["false"], "startTime": ["2019-04-14T20:53:20.000Z"], "endTime": ["2019-04-15T06:57:50.000Z"], "listingType": ["StoreInventory"], "gift": ["false"]}], "returnsAccepted": ["false"], "condition": [{"conditionId": ["1000"], "conditionDisplayName": ["New"]}], "isMultiVariationListing": ["false"], "topRatedListing": ["false"]}, {"itemId": ["183771676841"], "title": ["2018 MacBook Pro 13 Inch 2.3GHz 16gb 128gb"], "globalId": ["EBAY-US"], "primaryCategory": [{"categoryId": ["111422"], "categoryName": ["Apple Laptops"]}], "galleryURL": ["http://thumbs2.ebaystatic.com/m/myxP-iEP2buLFygNwqkVolA/140.jpg"], "viewItemURL": ["http://www.ebay.com/itm/2018-MacBook-Pro-13-Inch-2-3GHz-16gb-128gb-/183771676841"], "paymentMethod": ["PayPal"], "autoPay": ["false"], "postalCode": ["55102"], "location": ["Saint Paul,MN,USA"], "country": ["US"], "shippingInfo": [{"shippingType": ["Calculated"], "shipToLocations": ["Worldwide"], "expeditedShipping": ["true"], "oneDayShippingAvailable": ["false"], "handlingTime": ["3"]}], "sellingStatus": [{"currentPrice": [{"@currencyId": "USD", "__value__": "1200.0"}], "convertedCurrentPrice": [{"@currencyId": "USD", "__value__": "1200.0"}], "sellingState": ["EndedWithSales"]}], "listingInfo": [{"bestOfferEnabled": ["true"], "buyItNowAvailable": ["false"], "startTime": ["2019-04-12T14:10:04.000Z"], "endTime": ["2019-04-14T21:00:19.000Z"], "listingType": ["FixedPrice"], "gift": ["false"], "watchCount": ["2"]}], "returnsAccepted": ["false"], "condition": [{"conditionId": ["1000"], "conditionDisplayName": ["New"]}], "isMultiVariationListing": ["false"], "topRatedListing": ["false"]}, {"itemId": ["233194504279"], "title": ["2018 13\" Apple MacBook Pro 2.3GHz Quad i5 16GB RAM 512GB Touch ID/ Touch Bar"], "globalId": ["EBAY-US"], "subtitle": ["Sealed | Apple Care Plus Till 2022 | MSRP $2469 + Tax"], "primaryCategory": [{"categoryId": ["111422"], "categoryName": ["Apple Laptops"]}], "galleryURL": ["http://thumbs4.ebaystatic.com/m/m3UT0SYYaftoP8Y7N7de_QQ/140.jpg"], "viewItemURL": ["http://www.ebay.com/itm/2018-13-Apple-MacBook-Pro-2-3GHz-Quad-i5-16GB-RAM-512GB-Touch-ID-Touch-Bar-/233194504279"], "paymentMethod": ["PayPal"], "autoPay": ["true"], "postalCode": ["11214"], "location": ["Brooklyn,NY,USA"], "country": ["US"], "shippingInfo": [{"shippingServiceCost": [{"@currencyId": "USD", "__value__": "0.0"}], "shippingType": ["Free"], "shipToLocations": ["Worldwide"], "expeditedShipping": ["true"], "oneDayShippingAvailable": ["false"], "handlingTime": ["1"]}], "sellingStatus": [{"currentPrice": [{"@currencyId": "USD", "__value__": "2099.99"}], "convertedCurrentPrice": [{"@currencyId": "USD", "__value__": "2099.99"}], "sellingState": ["EndedWithSales"]}], "listingInfo": [{"bestOfferEnabled": ["false"], "buyItNowAvailable": ["false"], "startTime": ["2019-04-10T19:40:34.000Z"], "endTime": ["2019-04-14T02:14:06.000Z"], "listingType": ["StoreInventory"], "gift": ["false"], "watchCount": ["6"]}], "returnsAccepted": ["true"], "condition": [{"conditionId": ["1000"], "conditionDisplayName": ["New"]}], "isMultiVariationListing": ["false"], "topRatedListing": ["false"]}, {"itemId": ["264256832437"], "title": ["NEW 2018 MacBook Pro 13\" Touchbar - Intel i5 2.3GHz / 256GB - MR9Q2LL/A  SEALED!"], "globalId": ["EBAY-US"], "primaryCategory": [{"categoryId": ["111422"], "categoryName": ["Apple Laptops"]}], "galleryURL": ["http://thumbs2.ebaystatic.com/m/myD-ZF6UlL0RXYjDVHYXnLQ/140.jpg"], "viewItemURL": ["http://www.ebay.com/itm/NEW-2018-MacBook-Pro-13-Touchbar-Intel-i5-2-3GHz-256GB-MR9Q2LL-A-SEALED-/264256832437"], "paymentMethod": ["PayPal"], "autoPay": ["true"], "postalCode": ["90012"], "location": ["Los Angeles,CA,USA"], "country": ["US"], "shippingInfo": [{"shippingServiceCost": [{"@currencyId": "USD", "__value__": "0.0"}], "shippingType": ["Free"], "shipToLocations": ["Worldwide"], "expeditedShipping": ["false"], "oneDayShippingAvailable": ["false"], "handlingTime": ["1"]}], "sellingStatus": [{"currentPrice": [{"@currencyId": "USD", "__value__": "1649.95"}], "convertedCurrentPrice": [{"@currencyId": "USD", "__value__": "1649.95"}], "sellingState": ["EndedWithSales"]}], "listingInfo": [{"bestOfferEnabled": ["false"], "buyItNowAvailable": ["false"], "startTime": ["2019-03-27T06:49:50.000Z"], "endTime": ["2019-04-13T21:41:34.000Z"], "listingType": ["StoreInventory"], "gift": ["false"], "watchCount": ["8"]}], "returnsAccepted": ["false"], "condition": [{"conditionId": ["1000"], "conditionDisplayName": ["New"]}], "isMultiVariationListing": ["false"], "topRatedListing": ["false"]}, {"itemId": ["333153510267"], "title": ["MacBook Air Pro 13 2018 13.3\"/2.7GHz/8GB RAM/512GB Storage A1989"], "globalId": ["EBAY-US"], "primaryCategory": [{"categoryId": ["111422"], "categoryName": ["Apple Laptops"]}], "galleryURL": ["http://thumbs4.ebaystatic.com/m/mJ5kH4HuTplpdQox-J5nMlw/140.jpg"], "viewItemURL": ["http://www.ebay.com/itm/MacBook-Air-Pro-13-2018-13-3-2-7GHz-8GB-RAM-512GB-Storage-A1989-/333153510267"], "paymentMethod": ["PayPal"], "autoPay": ["false"], "postalCode": ["92618"], "location": ["Irvine,CA,USA"], "country": ["US"], "shippingInfo": [{"shippingServiceCost": [{"@currencyId": "USD", "__value__": "0.0"}], "shippingType": ["Free"], "shipToLocations": ["Worldwide"], "expeditedShipping": ["false"], "oneDayShippingAvailable": ["false"], "handlingTime": ["2"]}], "sellingStatus": [{"currentPrice": [{"@currencyId": "USD", "__value__": "1700.0"}], "convertedCurrentPrice": [{"@currencyId": "USD", "__value__": "1700.0"}], "sellingState": ["EndedWithSales"]}], "listingInfo": [{"bestOfferEnabled": ["true"], "buyItNowAvailable": ["false"], "startTime": ["2019-04-12T01:16:33.000Z"], "endTime": ["2019-04-13T21:37:05.000Z"], "listingType": ["FixedPrice"], "gift": ["false"], "watchCount": ["1"]}], "returnsAccepted": ["true"], "condition": [{"conditionId": ["1000"], "conditionDisplayName": ["New"]}], "isMultiVariationListing": ["false"], "topRatedListing": ["false"]}, {"itemId": ["264281857305"], "title": ["MacBook Pro Touch Bar 13\" MR9Q2LL/A i5 2.30GHz 8GB 256GB SSD Space Grey "], "globalId": ["EBAY-US"], "primaryCategory": [{"categoryId": ["111422"], "categoryName": ["Apple Laptops"]}], "galleryURL": ["http://thumbs2.ebaystatic.com/m/mh0aBj_LOpHVrvKEPRaIR4w/140.jpg"], "viewItemURL": ["http://www.ebay.com/itm/MacBook-Pro-Touch-Bar-13-MR9Q2LL-A-i5-2-30GHz-8GB-256GB-SSD-Space-Grey-/264281857305"], "productId": [{"@type": "ReferenceID", "__value__": "6027566072"}], "paymentMethod": ["PayPal"], "autoPay": ["true"], "postalCode": ["19116"], "location": ["Philadelphia,PA,USA"], "country": ["US"], "shippingInfo": [{"shippingServiceCost": [{"@currencyId": "USD", "__value__": "0.0"}], "shippingType": ["Free"], "shipToLocations": ["Worldwide"], "expeditedShipping": ["true"], "oneDayShippingAvailable": ["false"], "handlingTime": ["1"]}], "sellingStatus": [{"currentPrice": [{"@currencyId": "USD", "__value__": "1495.0"}], "convertedCurrentPrice": [{"@currencyId": "USD", "__value__": "1495.0"}], "sellingState": ["EndedWithSales"]}], "listingInfo": [{"bestOfferEnabled": ["false"], "buyItNowAvailable": ["false"], "startTime": ["2019-04-13T15:30:27.000Z"], "endTime": ["2019-04-13T15:50:14.000Z"], "listingType": ["FixedPrice"], "gift": ["false"]}], "returnsAccepted": ["true"], "condition": [{"conditionId": ["1000"], "conditionDisplayName": ["New"]}], "isMultiVariationListing": ["false"], "topRatedListing": ["false"]}, {"itemId": ["264280599107"], "title": ["Apple MacBook Pro 13-inch Mid 2018 i5 Quad-Core  2.3GHz 256GB SSD 16GB S.GRAY "], "globalId": ["EBAY-US"], "primaryCategory": [{"categoryId": ["111422"], "categoryName": ["Apple Laptops"]}], "galleryURL": ["http://thumbs4.ebaystatic.com/m/mclmLSF17EfovVSGm9-O4ww/140.jpg"], "viewItemURL": ["http://www.ebay.com/itm/Apple-MacBook-Pro-13-inch-Mid-2018-i5-Quad-Core-2-3GHz-256GB-SSD-16GB-S-GRAY-/264280599107"], "paymentMethod": ["PayPal"], "autoPay": ["true"], "postalCode": ["33179"], "location": ["Miami,FL,USA"], "country": ["US"], "shippingInfo": [{"shippingServiceCost": [{"@currencyId": "USD", "__value__": "0.0"}], "shippingType": ["FlatDomesticCalculatedInternational"], "shipToLocations": ["Worldwide"], "expeditedShipping": ["false"], "oneDayShippingAvailable": ["false"], "handlingTime": ["1"]}], "sellingStatus": [{"currentPrice": [{"@currencyId": "USD", "__value__": "1800.0"}], "convertedCurrentPrice": [{"@currencyId": "USD", "__value__": "1800.0"}], "sellingState": ["EndedWithSales"]}], "listingInfo": [{"bestOfferEnabled": ["true"], "buyItNowAvailable": ["false"], "startTime": ["2019-04-12T16:38:46.000Z"], "endTime": ["2019-04-13T12:27:53.000Z"], "listingType": ["StoreInventory"], "gift": ["false"], "watchCount": ["1"]}], "returnsAccepted": ["false"], "condition": [{"conditionId": ["1000"], "conditionDisplayName": ["New"]}], "isMultiVariationListing": ["false"], "topRatedListing": ["false"]}, {"itemId": ["323775037321"], "title": ["2018 New MacBook Pro 13\" SEALED  2.7GHz  512GB 16GB RAM Graphic 655 +APPLE CARE"], "globalId": ["EBAY-US"], "primaryCategory": [{"categoryId": ["111422"], "categoryName": ["Apple Laptops"]}], "galleryURL": ["http://thumbs2.ebaystatic.com/m/mX2sVfLEiXIsiPRLwQBZX-w/140.jpg"], "viewItemURL": ["http://www.ebay.com/itm/2018-New-MacBook-Pro-13-SEALED-2-7GHz-512GB-16GB-RAM-Graphic-655-APPLE-CARE-/323775037321"], "paymentMethod": ["PayPal"], "autoPay": ["true"], "location": ["USA"], "country": ["US"], "shippingInfo": [{"shippingServiceCost": [{"@currencyId": "USD", "__value__": "0.0"}], "shippingType": ["Free"], "shipToLocations": ["Worldwide"], "expeditedShipping": ["true"], "oneDayShippingAvailable": ["false"], "handlingTime": ["1"]}], "sellingStatus": [{"currentPrice": [{"@currencyId": "USD", "__value__": "2349.0"}], "convertedCurrentPrice": [{"@currencyId": "USD", "__value__": "2349.0"}], "sellingState": ["EndedWithSales"]}], "listingInfo": [{"bestOfferEnabled": ["false"], "buyItNowAvailable": ["false"], "startTime": ["2019-04-12T05:56:46.000Z"], "endTime": ["2019-04-12T21:08:30.000Z"], "listingType": ["FixedPrice"], "gift": ["false"]}], "returnsAccepted": ["true"], "condition": [{"conditionId": ["1000"], "conditionDisplayName": ["New"]}], "isMultiVariationListing": ["false"], "topRatedListing": ["true"]}, {"itemId": ["273804513813"], "title": ["Apple MacBook Pro 13\" MR9R2LL/A - A1989 Space Gray Laptop 512GB"], "globalId": ["EBAY-US"], "primaryCategory": [{"categoryId": ["111422"], "categoryName": ["Apple Laptops"]}], "galleryURL": ["http://thumbs2.ebaystatic.com/m/mk4KvwrLQUoCkcSihCf4BnA/140.jpg"], "viewItemURL": ["http://www.ebay.com/itm/Apple-MacBook-Pro-13-MR9R2LL-A-A1989-Space-Gray-Laptop-512GB-/273804513813"], "paymentMethod": ["PayPal"], "autoPay": ["true"], "postalCode": ["01515"], "location": ["East Brookfield,MA,USA"], "country": ["US"], "shippingInfo": [{"shippingServiceCost": [{"@currencyId": "USD", "__value__": "0.0"}], "shippingType": ["Free"], "shipToLocations": ["Worldwide"], "expeditedShipping": ["false"], "oneDayShippingAvailable": ["false"], "handlingTime": ["2"]}], "sellingStatus": [{"currentPrice": [{"@currencyId": "USD", "__value__": "1200.0"}], "convertedCurrentPrice": [{"@currencyId": "USD", "__value__": "1200.0"}], "sellingState": ["EndedWithSales"]}], "listingInfo": [{"bestOfferEnabled": ["true"], "buyItNowAvailable": ["false"], "startTime": ["2019-04-12T19:35:18.000Z"], "endTime": ["2019-04-12T19:44:29.000Z"], "listingType": ["FixedPrice"], "gift": ["false"]}], "returnsAccepted": ["false"], "condition": [{"conditionId": ["1000"], "conditionDisplayName": ["New"]}], "isMultiVariationListing": ["false"], "topRatedListing": ["false"]}, {"itemId": ["163629797276"], "title": ["Apple MacBook Pro Z0V70006T 13\" Display Intel Core I5 - Space Gray"], "globalId": ["EBAY-US"], "primaryCategory": [{"categoryId": ["111422"], "categoryName": ["Apple Laptops"]}], "galleryURL": ["http://thumbs1.ebaystatic.com/m/miGPvAPHUkAJ4dkfVn6H_Wg/140.jpg"], "viewItemURL": ["http://www.ebay.com/itm/Apple-MacBook-Pro-Z0V70006T-13-Display-Intel-Core-I5-Space-Gray-/163629797276"], "paymentMethod": ["PayPal"], "autoPay": ["true"], "postalCode": ["76017"], "location": ["Arlington,TX,USA"], "country": ["US"], "shippingInfo": [{"shippingServiceCost": [{"@currencyId": "USD", "__value__": "0.0"}], "shippingType": ["FreePickup"], "shipToLocations": ["Worldwide"], "expeditedShipping": ["false"], "oneDayShippingAvailable": ["false"], "handlingTime": ["2"]}], "sellingStatus": [{"currentPrice": [{"@currencyId": "USD", "__value__": "1750.0"}], "convertedCurrentPrice": [{"@currencyId": "USD", "__value__": "1750.0"}], "sellingState": ["EndedWithSales"]}], "listingInfo": [{"bestOfferEnabled": ["true"], "buyItNowAvailable": ["false"], "startTime": ["2019-04-02T15:29:16.000Z"], "endTime": ["2019-04-12T01:46:23.000Z"], "listingType": ["FixedPrice"], "gift": ["false"], "watchCount": ["1"]}], "returnsAccepted": ["false"], "condition": [{"conditionId": ["1000"], "conditionDisplayName": ["New"]}], "isMultiVariationListing": ["false"], "topRatedListing": ["false"]}, {"itemId": ["143201662662"], "title": ["2018 13\" Apple MacBook Pro RETINA 2.3 GHz QUAD Core i5 512GB SSD 8GB RAM SEALED "], "globalId": ["EBAY-US"], "primaryCategory": [{"categoryId": ["111422"], "categoryName": ["Apple Laptops"]}], "galleryURL": ["http://thumbs3.ebaystatic.com/m/mG2641bxV6-S8YP2CamX_jw/140.jpg"], "viewItemURL": ["http://www.ebay.com/itm/2018-13-Apple-MacBook-Pro-RETINA-2-3-GHz-QUAD-Core-i5-512GB-SSD-8GB-RAM-SEALED-/143201662662"], "productId": [{"@type": "ReferenceID", "__value__": "22028679228"}], "paymentMethod": ["PayPal"], "autoPay": ["true"], "postalCode": ["92123"], "location": ["San Diego,CA,USA"], "country": ["US"], "shippingInfo": [{"shippingServiceCost": [{"@currencyId": "USD", "__value__": "0.0"}], "shippingType": ["Free"], "shipToLocations": ["Worldwide"], "expeditedShipping": ["true"], "oneDayShippingAvailable": ["true"], "handlingTime": ["1"]}], "sellingStatus": [{"currentPrice": [{"@currencyId": "USD", "__value__": "1719.0"}], "convertedCurrentPrice": [{"@currencyId": "USD", "__value__": "1719.0"}], "sellingState": ["EndedWithSales"]}], "listingInfo": [{"bestOfferEnabled": ["false"], "buyItNowAvailable": ["false"], "startTime": ["2019-04-04T17:22:48.000Z"], "endTime": ["2019-04-11T13:06:30.000Z"], "listingType": ["StoreInventory"], "gift": ["false"], "watchCount": ["8"]}], "returnsAccepted": ["true"], "condition": [{"conditionId": ["1000"], "conditionDisplayName": ["New"]}], "isMultiVariationListing": ["false"], "topRatedListing": ["true"]}, {"itemId": ["333149704453"], "title": ["NEW WARRANTY Apple MacBook Pro 13\" w/ Touch Bar i5 8GB 256GB Silver - MR9U2LL/A"], "globalId": ["EBAY-US"], "primaryCategory": [{"categoryId": ["111422"], "categoryName": ["Apple Laptops"]}], "galleryURL": ["http://thumbs2.ebaystatic.com/m/myX3rqKN0gowmCfwvXh6pWA/140.jpg"], "viewItemURL": ["http://www.ebay.com/itm/NEW-WARRANTY-Apple-MacBook-Pro-13-w-Touch-Bar-i5-8GB-256GB-Silver-MR9U2LL-A-/333149704453"], "productId": [{"@type": "ReferenceID", "__value__": "12027548069"}], "paymentMethod": ["PayPal"], "autoPay": ["true"], "postalCode": ["48306"], "location": ["Rochester,MI,USA"], "country": ["US"], "shippingInfo": [{"shippingServiceCost": [{"@currencyId": "USD", "__value__": "0.0"}], "shippingType": ["Free"], "shipToLocations": ["Worldwide"], "expeditedShipping": ["false"], "oneDayShippingAvailable": ["false"], "handlingTime": ["1"]}], "sellingStatus": [{"currentPrice": [{"@currencyId": "USD", "__value__": "1604.99"}], "convertedCurrentPrice": [{"@currencyId": "USD", "__value__": "1604.99"}], "sellingState": ["EndedWithSales"]}], "listingInfo": [{"bestOfferEnabled": ["false"], "buyItNowAvailable": ["false"], "startTime": ["2019-04-09T00:13:14.000Z"], "endTime": ["2019-04-11T05:48:56.000Z"], "listingType": ["StoreInventory"], "gift": ["false"]}], "returnsAccepted": ["true"], "condition": [{"conditionId": ["1000"], "conditionDisplayName": ["New"]}], "isMultiVariationListing": ["false"], "topRatedListing": ["false"]}, {"itemId": ["323769782909"], "title": ["Rare Sealed Apple MacBook Pro 13in 2018 2.7GHz i7 16GB RAM 512GB SSD Touchbar"], "globalId": ["EBAY-US"], "primaryCategory": [{"categoryId": ["111422"], "categoryName": ["Apple Laptops"]}], "galleryURL": ["http://thumbs2.ebaystatic.com/m/mfEIpREknki8rrKEweWMbRQ/140.jpg"], "viewItemURL": ["http://www.ebay.com/itm/Rare-Sealed-Apple-MacBook-Pro-13in-2018-2-7GHz-i7-16GB-RAM-512GB-SSD-Touchbar-/323769782909"], "paymentMethod": ["PayPal"], "autoPay": ["false"], "postalCode": ["77494"], "location": ["Katy,TX,USA"], "country": ["US"], "shippingInfo": [{"shippingServiceCost": [{"@currencyId": "USD", "__value__": "35.0"}], "shippingType": ["Flat"], "shipToLocations": ["Worldwide"], "expeditedShipping": ["true"], "oneDayShippingAvailable": ["false"], "handlingTime": ["2"]}], "sellingStatus": [{"currentPrice": [{"@currencyId": "USD", "__value__": "2399.98"}], "convertedCurrentPrice": [{"@currencyId": "USD", "__value__": "2399.98"}], "sellingState": ["EndedWithSales"]}], "listingInfo": [{"bestOfferEnabled": ["false"], "buyItNowAvailable": ["false"], "startTime": ["2019-04-07T15:57:55.000Z"], "endTime": ["2019-04-10T10:24:53.000Z"], "listingType": ["StoreInventory"], "gift": ["false"], "watchCount": ["1"]}], "returnsAccepted": ["false"], "condition": [{"conditionId": ["1000"], "conditionDisplayName": ["New"]}], "isMultiVariationListing": ["false"], "topRatedListing": ["false"]}, {"itemId": ["264258791078"], "title": ["2018 Apple Macbook Pro 13\" Intel Core i5 2.3GHz -8GB -256GB SSD - W/ Touchbar"], "globalId": ["EBAY-US"], "primaryCategory": [{"categoryId": ["111422"], "categoryName": ["Apple Laptops"]}], "galleryURL": ["http://thumbs3.ebaystatic.com/m/mMexEYASPg86Qr7P9RZIpdw/140.jpg"], "viewItemURL": ["http://www.ebay.com/itm/2018-Apple-Macbook-Pro-13-Intel-Core-i5-2-3GHz-8GB-256GB-SSD-W-Touchbar-/264258791078"], "productId": [{"@type": "ReferenceID", "__value__": "5021491514"}], "paymentMethod": ["PayPal"], "autoPay": ["true"], "location": ["USA"], "country": ["US"], "shippingInfo": [{"shippingServiceCost": [{"@currencyId": "USD", "__value__": "0.0"}], "shippingType": ["Free"], "shipToLocations": ["Worldwide"], "expeditedShipping": ["true"], "oneDayShippingAvailable": ["false"], "handlingTime": ["1"]}], "sellingStatus": [{"currentPrice": [{"@currencyId": "USD", "__value__": "1599.0"}], "convertedCurrentPrice": [{"@currencyId": "USD", "__value__": "1599.0"}], "sellingState": ["EndedWithSales"]}], "listingInfo": [{"bestOfferEnabled": ["false"], "buyItNowAvailable": ["false"], "startTime": ["2019-03-28T15:55:49.000Z"], "endTime": ["2019-04-09T05:18:11.000Z"], "listingType": ["StoreInventory"], "gift": ["false"], "watchCount": ["26"]}], "returnsAccepted": ["true"], "condition": [{"conditionId": ["1000"], "conditionDisplayName": ["New"]}], "isMultiVariationListing": ["false"], "topRatedListing": ["true"]}, {"itemId": ["113707255904"], "title": ["2018 Apple MacBook Pro Touch Bar Space Gray 13\u201d Laptop 256GB  BRAND NEW SEALED"], "globalId": ["EBAY-US"], "primaryCategory": [{"categoryId": ["111422"], "categoryName": ["Apple Laptops"]}], "galleryURL": ["http://thumbs1.ebaystatic.com/m/mzXrME6mlqMHHiWVWbyh6_w/140.jpg"], "viewItemURL": ["http://www.ebay.com/itm/2018-Apple-MacBook-Pro-Touch-Bar-Space-Gray-13-Laptop-256GB-BRAND-NEW-SEALED-/113707255904"], "paymentMethod": ["PayPal"], "autoPay": ["true"], "postalCode": ["80906"], "location": ["Colorado Springs,CO,USA"], "country": ["US"], "shippingInfo": [{"shippingServiceCost": [{"@currencyId": "USD", "__value__": "0.0"}], "shippingType": ["Free"], "shipToLocations": ["Worldwide"], "expeditedShipping": ["true"], "oneDayShippingAvailable": ["true"], "handlingTime": ["0"]}], "sellingStatus": [{"currentPrice": [{"@currencyId": "USD", "__value__": "1599.0"}], "convertedCurrentPrice": [{"@currencyId": "USD", "__value__": "1599.0"}], "sellingState": ["EndedWithSales"]}], "listingInfo": [{"bestOfferEnabled": ["false"], "buyItNowAvailable": ["false"], "startTime": ["2019-04-03T21:41:50.000Z"], "endTime": ["2019-04-09T04:08:53.000Z"], "listingType": ["StoreInventory"], "gift": ["false"], "watchCount": ["7"]}], "returnsAccepted": ["true"], "condition": [{"conditionId": ["1000"], "conditionDisplayName": ["New"]}], "isMultiVariationListing": ["false"], "topRatedListing": ["true"]}, {"itemId": ["233188204378"], "title": ["2018 13\" Apple MacBook Pro 2.3GHz Quad i5 16GB RAM 512GB Touch ID/ Touch Bar"], "globalId": ["EBAY-US"], "subtitle": ["Sealed | Apple Care Plus Till 2022 | MSRP $2469 + Tax"], "primaryCategory": [{"categoryId": ["111422"], "categoryName": ["Apple Laptops"]}], "galleryURL": ["http://thumbs3.ebaystatic.com/m/m3UT0SYYaftoP8Y7N7de_QQ/140.jpg"], "viewItemURL": ["http://www.ebay.com/itm/2018-13-Apple-MacBook-Pro-2-3GHz-Quad-i5-16GB-RAM-512GB-Touch-ID-Touch-Bar-/233188204378"], "paymentMethod": ["PayPal"], "autoPay": ["true"], "postalCode": ["11214"], "location": ["Brooklyn,NY,USA"], "country": ["US"], "shippingInfo": [{"shippingServiceCost": [{"@currencyId": "USD", "__value__": "0.0"}], "shippingType": ["Free"], "shipToLocations": ["Worldwide"], "expeditedShipping": ["true"], "oneDayShippingAvailable": ["false"], "handlingTime": ["1"]}], "sellingStatus": [{"currentPrice": [{"@currencyId": "USD", "__value__": "2099.99"}], "convertedCurrentPrice": [{"@currencyId": "USD", "__value__": "2099.99"}], "sellingState": ["EndedWithSales"]}], "listingInfo": [{"bestOfferEnabled": ["false"], "buyItNowAvailable": ["false"], "startTime": ["2019-04-03T22:27:43.000Z"], "endTime": ["2019-04-08T21:42:46.000Z"], "listingType": ["StoreInventory"], "gift": ["false"], "watchCount": ["5"]}], "returnsAccepted": ["true"], "condition": [{"conditionId": ["1000"], "conditionDisplayName": ["New"]}], "isMultiVariationListing": ["false"], "topRatedListing": ["false"]}, {"itemId": ["153442803587"], "title": ["Apple MacBook Pro 13-inch  2018 i5 Quad-Core  2.3GHz 1TB SSD 16GB S.GRAY "], "globalId": ["EBAY-US"], "primaryCategory": [{"categoryId": ["111422"], "categoryName": ["Apple Laptops"]}], "galleryURL": ["http://thumbs4.ebaystatic.com/m/mAIXlJF5PPiy6rVNKe2UTkg/140.jpg"], "viewItemURL": ["http://www.ebay.com/itm/Apple-MacBook-Pro-13-inch-2018-i5-Quad-Core-2-3GHz-1TB-SSD-16GB-S-GRAY-/153442803587"], "paymentMethod": ["PayPal"], "autoPay": ["false"], "postalCode": ["60616"], "location": ["Chicago,IL,USA"], "country": ["US"], "shippingInfo": [{"shippingType": ["Calculated"], "shipToLocations": ["Worldwide"], "expeditedShipping": ["true"], "oneDayShippingAvailable": ["false"], "handlingTime": ["2"]}], "sellingStatus": [{"currentPrice": [{"@currencyId": "USD", "__value__": "2059.99"}], "convertedCurrentPrice": [{"@currencyId": "USD", "__value__": "2059.99"}], "sellingState": ["EndedWithSales"]}], "listingInfo": [{"bestOfferEnabled": ["false"], "buyItNowAvailable": ["false"], "startTime": ["2019-04-07T03:17:27.000Z"], "endTime": ["2019-04-08T19:47:39.000Z"], "listingType": ["FixedPrice"], "gift": ["false"], "watchCount": ["3"]}], "returnsAccepted": ["true"], "condition": [{"conditionId": ["1000"], "conditionDisplayName": ["New"]}], "isMultiVariationListing": ["false"], "topRatedListing": ["false"]}, {"itemId": ["293031008734"], "title": ["SEALED 2018 SILVER Apple MacBook Pro A1989 13 inch 256GB i5 8th Gen 2.3GHz 8GB"], "globalId": ["EBAY-US"], "primaryCategory": [{"categoryId": ["111422"], "categoryName": ["Apple Laptops"]}], "galleryURL": ["http://thumbs3.ebaystatic.com/m/mcjHE7z3LB6PPU3pHF38IqQ/140.jpg"], "viewItemURL": ["http://www.ebay.com/itm/SEALED-2018-SILVER-Apple-MacBook-Pro-A1989-13-inch-256GB-i5-8th-Gen-2-3GHz-8GB-/293031008734"], "productId": [{"@type": "ReferenceID", "__value__": "12027548069"}], "paymentMethod": ["PayPal"], "autoPay": ["true"], "postalCode": ["78526"], "location": ["Brownsville,TX,USA"], "country": ["US"], "shippingInfo": [{"shippingServiceCost": [{"@currencyId": "USD", "__value__": "0.0"}], "shippingType": ["Free"], "shipToLocations": ["Worldwide"], "expeditedShipping": ["true"], "oneDayShippingAvailable": ["false"], "handlingTime": ["2"]}], "sellingStatus": [{"currentPrice": [{"@currencyId": "USD", "__value__": "1619.99"}], "convertedCurrentPrice": [{"@currencyId": "USD", "__value__": "1619.99"}], "sellingState": ["EndedWithSales"]}], "listingInfo": [{"bestOfferEnabled": ["false"], "buyItNowAvailable": ["false"], "startTime": ["2019-04-01T16:06:24.000Z"], "endTime": ["2019-04-08T02:02:36.000Z"], "listingType": ["StoreInventory"], "gift": ["false"], "watchCount": ["1"]}], "returnsAccepted": ["true"], "condition": [{"conditionId": ["1000"], "conditionDisplayName": ["New"]}], "isMultiVariationListing": ["false"], "topRatedListing": ["false"]}, {"itemId": ["233176045203"], "title": ["2018 Apple MacBook Pro 13\" i5 QC 2.3Ghz 8GB 512GB MR9R2LL/A AppleCare+ till 2021"], "globalId": ["EBAY-US"], "subtitle": ["Sealed | Apple Care Plus Till 2021 | MSRP $2269 + Tax"], "primaryCategory": [{"categoryId": ["111422"], "categoryName": ["Apple Laptops"]}], "galleryURL": ["http://thumbs4.ebaystatic.com/m/m3UT0SYYaftoP8Y7N7de_QQ/140.jpg"], "viewItemURL": ["http://www.ebay.com/itm/2018-Apple-MacBook-Pro-13-i5-QC-2-3Ghz-8GB-512GB-MR9R2LL-A-AppleCare-till-2021-/233176045203"], "productId": [{"@type": "ReferenceID", "__value__": "10022297999"}], "paymentMethod": ["PayPal"], "autoPay": ["true"], "postalCode": ["11214"], "location": ["Brooklyn,NY,USA"], "country": ["US"], "shippingInfo": [{"shippingServiceCost": [{"@currencyId": "USD", "__value__": "0.0"}], "shippingType": ["Free"], "shipToLocations": ["Worldwide"], "expeditedShipping": ["true"], "oneDayShippingAvailable": ["false"], "handlingTime": ["1"]}], "sellingStatus": [{"currentPrice": [{"@currencyId": "USD", "__value__": "1779.99"}], "convertedCurrentPrice": [{"@currencyId": "USD", "__value__": "1779.99"}], "sellingState": ["EndedWithSales"]}], "listingInfo": [{"bestOfferEnabled": ["false"], "buyItNowAvailable": ["false"], "startTime": ["2019-03-22T21:49:28.000Z"], "endTime": ["2019-04-08T01:05:53.000Z"], "listingType": ["StoreInventory"], "gift": ["false"], "watchCount": ["8"]}], "returnsAccepted": ["true"], "condition": [{"conditionId": ["1000"], "conditionDisplayName": ["New"]}], "isMultiVariationListing": ["false"], "topRatedListing": ["false"]}, {"itemId": ["223475009154"], "title": ["2018 Apple Macbook Pro 13\" Intel Core i5 2.3GHz -8GB -256GB SSD"], "globalId": ["EBAY-US"], "primaryCategory": [{"categoryId": ["111422"], "categoryName": ["Apple Laptops"]}], "galleryURL": ["http://thumbs3.ebaystatic.com/m/mSl0Ba04jyeR1fapedVm1Ww/140.jpg"], "viewItemURL": ["http://www.ebay.com/itm/2018-Apple-Macbook-Pro-13-Intel-Core-i5-2-3GHz-8GB-256GB-SSD-/223475009154"], "productId": [{"@type": "ReferenceID", "__value__": "5021491514"}], "paymentMethod": ["PayPal"], "autoPay": ["false"], "postalCode": ["04103"], "location": ["Portland,ME,USA"], "country": ["US"], "shippingInfo": [{"shippingServiceCost": [{"@currencyId": "USD", "__value__": "0.0"}], "shippingType": ["Free"], "shipToLocations": ["Worldwide"], "expeditedShipping": ["true"], "oneDayShippingAvailable": ["false"], "handlingTime": ["3"]}], "sellingStatus": [{"currentPrice": [{"@currencyId": "USD", "__value__": "1400.0"}], "convertedCurrentPrice": [{"@currencyId": "USD", "__value__": "1400.0"}], "sellingState": ["EndedWithSales"]}], "listingInfo": [{"bestOfferEnabled": ["true"], "buyItNowAvailable": ["false"], "startTime": ["2019-04-07T23:00:51.000Z"], "endTime": ["2019-04-07T23:06:43.000Z"], "listingType": ["FixedPrice"], "gift": ["false"]}], "returnsAccepted": ["false"], "condition": [{"conditionId": ["1000"], "conditionDisplayName": ["New"]}], "isMultiVariationListing": ["false"], "topRatedListing": ["false"]}, {"itemId": ["293033738762"], "title": ["Apple Macbook Pro 13, 2018, 2.7ghz Core i7 16gb, 1TB"], "globalId": ["EBAY-US"], "subtitle": ["Brand new Sealed part num: Z0V80006K"], "primaryCategory": [{"categoryId": ["111422"], "categoryName": ["Apple Laptops"]}], "galleryURL": ["http://thumbs3.ebaystatic.com/m/mvll6T1d7R3-5nAzquNT38w/140.jpg"], "viewItemURL": ["http://www.ebay.com/itm/Apple-Macbook-Pro-13-2018-2-7ghz-Core-i7-16gb-1TB-/293033738762"], "paymentMethod": ["PayPal"], "autoPay": ["false"], "postalCode": ["10018"], "location": ["New York,NY,USA"], "country": ["US"], "shippingInfo": [{"shippingServiceCost": [{"@currencyId": "USD", "__value__": "0.0"}], "shippingType": ["Free"], "shipToLocations": ["Worldwide"], "expeditedShipping": ["true"], "oneDayShippingAvailable": ["false"], "handlingTime": ["3"]}], "sellingStatus": [{"currentPrice": [{"@currencyId": "USD", "__value__": "2550.0"}], "convertedCurrentPrice": [{"@currencyId": "USD", "__value__": "2550.0"}], "sellingState": ["EndedWithSales"]}], "listingInfo": [{"bestOfferEnabled": ["true"], "buyItNowAvailable": ["false"], "startTime": ["2019-04-03T12:27:26.000Z"], "endTime": ["2019-04-05T22:37:12.000Z"], "listingType": ["FixedPrice"], "gift": ["false"], "watchCount": ["5"]}], "returnsAccepted": ["false"], "condition": [{"conditionId": ["1000"], "conditionDisplayName": ["New"]}], "isMultiVariationListing": ["false"], "topRatedListing": ["false"]}, {"itemId": ["372640054137"], "title": ["SEALED 2018 13\" Apple MacBook Pro RETINA 2.3 GHz QUAD Core i5 512GB SSD 8GB RAM!"], "globalId": ["EBAY-US"], "primaryCategory": [{"categoryId": ["111422"], "categoryName": ["Apple Laptops"]}], "galleryURL": ["http://thumbs2.ebaystatic.com/m/mM3L9SBa6NxY-sQsEuNGnqQ/140.jpg"], "viewItemURL": ["http://www.ebay.com/itm/SEALED-2018-13-Apple-MacBook-Pro-RETINA-2-3-GHz-QUAD-Core-i5-512GB-SSD-8GB-RAM-/372640054137"], "productId": [{"@type": "ReferenceID", "__value__": "22028679228"}], "paymentMethod": ["PayPal"], "autoPay": ["true"], "postalCode": ["92123"], "location": ["San Diego,CA,USA"], "country": ["US"], "shippingInfo": [{"shippingServiceCost": [{"@currencyId": "USD", "__value__": "0.0"}], "shippingType": ["Free"], "shipToLocations": ["Worldwide"], "expeditedShipping": ["true"], "oneDayShippingAvailable": ["true"], "handlingTime": ["1"]}], "sellingStatus": [{"currentPrice": [{"@currencyId": "USD", "__value__": "1758.0"}], "convertedCurrentPrice": [{"@currencyId": "USD", "__value__": "1758.0"}], "sellingState": ["EndedWithSales"]}], "listingInfo": [{"bestOfferEnabled": ["false"], "buyItNowAvailable": ["false"], "startTime": ["2019-03-29T18:29:35.000Z"], "endTime": ["2019-04-05T21:31:19.000Z"], "listingType": ["StoreInventory"], "gift": ["false"], "watchCount": ["4"]}], "returnsAccepted": ["true"], "condition": [{"conditionId": ["1000"], "conditionDisplayName": ["New"]}], "isMultiVariationListing": ["false"], "topRatedListing": ["true"]}]}], "paginationOutput": [{"pageNumber": ["2"], "entriesPerPage": ["100"], "totalPages": ["2"], "totalEntries": ["159"]}]}]}